[{"序號": 1, "國別地區": "日本", "中文片名": "我的英雄學院劇場版：英雄新世紀", "上映日期": "2020/04/01", "申請人": "薩摩亞商羚邦(亞洲)有限公司台灣分公司", "出品": "Toho Co., Ltd.", "上映院數": 68, "銷售票數": 13632, "週票數變動率": "-41.27%", "銷售金額": 3211734, "累計銷售票數": 36845, "累計銷售金額": 8666348}, {"序號": 2, "國別地區": "日本", "中文片名": "犬鳴村", "上映日期": "2020/04/01", "申請人": "車庫娛樂股份有限公司", "出品": "TOEI COMPANY, LTD.", "上映院數": 50, "銷售票數": 8596, "週票數變動率": "-43.96%", "銷售金額": 2025251, "累計銷售票數": 23936, "累計銷售金額": 5621722}, {"序號": 3, "國別地區": "美國", "中文片名": "間諜速成班", "上映日期": "2020/04/01", "申請人": "英屬蓋曼群島商威望國際娛樂股份有限公司台灣分公司", "出品": "STX Productions, LLC", "上映院數": 87, "銷售票數": 5778, "週票數變動率": "-41.81%", "銷售金額": 1301645, "累計銷售票數": 15708, "累計銷售金額": 3545394}, {"序號": 4, "國別地區": "美國", "中文片名": "魔髮精靈唱遊世界", "上映日期": "2020/04/01", "申請人": "美商美國環球影片股份有限公司台灣分公司", "出品": "UNIVERSAL INTERNATIONAL FILMS LLC", "上映院數": 88, "銷售票數": 2436, "週票數變動率": "-65.34%", "銷售金額": 555297, "累計銷售票數": 9465, "累計銷售金額": 2157514}, {"序號": 5, "國別地區": "墨西哥", "中文片名": "羊男的迷宮", "上映日期": "2020/04/01", "申請人": "車庫娛樂股份有限公司", "出品": "(法國)WILD BUNCH", "上映院數": 16, "銷售票數": 1236, "週票數變動率": "-14.40%", "銷售金額": 286575, "累計銷售票數": 2680, "累計銷售金額": 623364}, {"序號": 6, "國別地區": "日本", "中文片名": "火口的二人", "上映日期": "2020/04/01", "申請人": "采昌國際多媒體股份有限公司", "出品": "Hakuhodo DY music & pictures Inc.", "上映院數": 16, "銷售票數": 1141, "週票數變動率": "-31.92%", "銷售金額": 262547, "累計銷售票數": 2817, "累計銷售金額": 642899}, {"序號": 7, "國別地區": "泰國", "中文片名": "冤鴦大盜", "上映日期": "2020/04/01", "申請人": "英屬維京群島商高捷全球開發有限公司 台灣分公司", "出品": "Mono Film Company Limited", "上映院數": 40, "銷售票數": 610, "週票數變動率": "-59.01%", "銷售金額": 134678, "累計銷售票數": 2098, "累計銷售金額": 460097}, {"序號": 8, "國別地區": "澳洲", "中文片名": "小魔花", "上映日期": "2020/04/01", "申請人": "東昊影業有限公司", "出品": "SOCIETE PARISIENNE DE PRODUCTION", "上映院數": 19, "銷售票數": 385, "週票數變動率": "-35.51%", "銷售金額": 83670, "累計銷售票數": 982, "累計銷售金額": 213574}, {"序號": 9, "國別地區": "德國", "中文片名": "馬丁伊登", "上映日期": "2020/04/01", "申請人": "海鵬影業有限公司", "出品": "The Match Factory", "上映院數": 12, "銷售票數": 351, "週票數變動率": "-40.61%", "銷售金額": 70912, "累計銷售票數": 942, "累計銷售金額": 189604}, {"序號": 10, "國別地區": "美國", "中文片名": "拾光人生", "上映日期": "2020/04/01", "申請人": "車庫娛樂股份有限公司", "出品": "(英國)RELIANCE ENTERTAINMENT PRODUCTIONS 9 LTD.", "上映院數": 15, "銷售票數": 252, "週票數變動率": "-43.24%", "銷售金額": 54507, "累計銷售票數": 696, "累計銷售金額": 152710}, {"序號": 11, "國別地區": "日本", "中文片名": "猛鬼大師收工沒?", "上映日期": "2020/04/01", "申請人": "亮點國際影業有限公司", "出品": "SDP INC.", "上映院數": 21, "銷售票數": 99, "週票數變動率": "-73.53%", "銷售金額": 21235, "累計銷售票數": 473, "累計銷售金額": 111768}, {"序號": 12, "國別地區": "美國", "中文片名": "託陰2：布拉姆回來了", "上映日期": "2020/03/27", "申請人": "英屬蓋曼群島商威望國際娛樂股份有限公司台灣分公司", "出品": "STX Productions, LLC", "上映院數": 88, "銷售票數": 2034, "週票數變動率": "-71.19%", "銷售金額": 455460, "累計銷售票數": 16950, "累計銷售金額": 3852323}, {"序號": 13, "國別地區": "南韓", "中文片名": "抓住救命稻草的野獸們", "上映日期": "2020/03/27", "申請人": "薩摩亞商雄讚股份有限公司台灣分公司", "出品": "M-Line Distribution Corportation", "上映院數": 75, "銷售票數": 1908, "週票數變動率": "-69.48%", "銷售金額": 428230, "累計銷售票數": 14137, "累計銷售金額": 3163858}, {"序號": 14, "國別地區": "美國", "中文片名": "絕命直播", "上映日期": "2020/03/27", "申請人": "香港商甲上娛樂有限公司台灣分公司", "出品": "Live Movie, LLC", "上映院數": 80, "銷售票數": 1807, "週票數變動率": "-70.29%", "銷售金額": 413171, "累計銷售票數": 15355, "累計銷售金額": 3491756}, {"序號": 15, "國別地區": "日本", "中文片名": "Re：從零開始的異世界生活-外傳篇章電影", "上映日期": "2020/03/27", "申請人": "木棉花國際股份有限公司", "出品": "KADOKAWA SHOTEN CO., LTD.", "上映院數": 18, "銷售票數": 1502, "週票數變動率": "-69.44%", "銷售金額": 332532, "累計銷售票數": 12009, "累計銷售金額": 2669714}, {"序號": 16, "國別地區": "美國", "中文片名": "無聲救援", "上映日期": "2020/03/27", "申請人": "車庫娛樂股份有限公司", "出品": "ROCKET SCIENCE INDUSTRIES LTD.", "上映院數": 47, "銷售票數": 660, "週票數變動率": "-76.41%", "銷售金額": 153010, "累計銷售票數": 6779, "累計銷售金額": 1552965}, {"序號": 17, "國別地區": "日本", "中文片名": "最初的晚餐", "上映日期": "2020/03/27", "申請人": "威視股份有限公司", "出品": "KADOKAWA CORPORATION", "上映院數": 28, "銷售票數": 188, "週票數變動率": "-74.03%", "銷售金額": 41448, "累計銷售票數": 1703, "累計銷售金額": 385581}, {"序號": 18, "國別地區": "法國", "中文片名": "迷雁返家路", "上映日期": "2020/03/27", "申請人": "可樂藝術文創股份有限公司", "出品": "Société Nouvelle de Distribution (SND)", "上映院數": 26, "銷售票數": 162, "週票數變動率": "-76.89%", "銷售金額": 34540, "累計銷售票數": 1752, "累計銷售金額": 383223}, {"序號": 19, "國別地區": "日本", "中文片名": "記憶屋", "上映日期": "2020/03/27", "申請人": "天馬行空數位有限公司", "出品": "Shochiku Co., Ltd", "上映院數": 16, "銷售票數": 141, "週票數變動率": "-76.92%", "銷售金額": 31869, "累計銷售票數": 1737, "累計銷售金額": 398636}, {"序號": 20, "國別地區": "美國", "中文片名": "我的學生都是配樂大師", "上映日期": "2020/03/27", "申請人": "造次文化有限公司", "出品": "Cardinal XD, LLC", "上映院數": 7, "銷售票數": 82, "週票數變動率": "-76.37%", "銷售金額": 18520, "累計銷售票數": 645, "累計銷售金額": 147659}, {"序號": 21, "國別地區": "法國", "中文片名": "聲入奇境：經典配樂大師", "上映日期": "2020/03/27", "申請人": "佳映娛樂國際股份有限公司", "出品": "Wide House", "上映院數": 7, "銷售票數": 66, "週票數變動率": "-63.93%", "銷售金額": 14570, "累計銷售票數": 489, "累計銷售金額": 109640}, {"序號": 22, "國別地區": "加拿大", "中文片名": "鏡中驚魂", "上映日期": "2020/03/27", "申請人": "暗光鳥有限公司", "出品": "GEM ENTERTAINMENT, KFT.", "上映院數": 6, "銷售票數": 62, "週票數變動率": "-62.42%", "銷售金額": 14013, "累計銷售票數": 407, "累計銷售金額": 90239}, {"序號": 23, "國別地區": "英國", "中文片名": "我們的家不是我們的家", "上映日期": "2020/03/27", "申請人": "天馬行空數位有限公司", "出品": "PROTAGONIST PICTURES LIMITED", "上映院數": 7, "銷售票數": 57, "週票數變動率": "-66.86%", "銷售金額": 12140, "累計銷售票數": 535, "累計銷售金額": 117184}, {"序號": 24, "國別地區": "日本", "中文片名": "東京喰種S", "上映日期": "2020/03/27", "申請人": "車庫娛樂股份有限公司", "出品": "SHOCHIKU CO., LTD.", "上映院數": 14, "銷售票數": 38, "週票數變動率": "-87.21%", "銷售金額": 9340, "累計銷售票數": 759, "累計銷售金額": 178881}, {"序號": 25, "國別地區": "法國", "中文片名": "奧斯卡配樂大師：亞歷山大戴斯培", "上映日期": "2020/03/27", "申請人": "佳映娛樂國際股份有限公司", "出品": "Wide House", "上映院數": 2, "銷售票數": 37, "週票數變動率": "-64.42%", "銷售金額": 7335, "累計銷售票數": 187, "累計銷售金額": 39937}, {"序號": 26, "國別地區": "中華民國", "中文片名": "我不流行二十年", "上映日期": "2020/03/20", "申請人": "韶光電影有限公司", "出品": "角頭文化事業股份有限公司", "上映院數": 5, "銷售票數": 156, "週票數變動率": "0.00%", "銷售金額": 41648, "累計銷售票數": 833, "累計銷售金額": 189848}, {"序號": 27, "國別地區": "美國", "中文片名": "依然相信", "上映日期": "2020/03/20", "申請人": "車庫娛樂股份有限公司", "出品": "LIONS GATE INTERNATIONAL (UK) LIMITED", "上映院數": 15, "銷售票數": 110, "週票數變動率": "-78.26%", "銷售金額": 27728, "累計銷售票數": 5646, "累計銷售金額": 1339701}, {"序號": 28, "國別地區": "日本", "中文片名": "搖滾師匠：細野晴臣", "上映日期": "2020/03/20", "申請人": "中影股份有限公司", "出品": "日活株式會社(NIKKATSU CORPORATION)", "上映院數": 4, "銷售票數": 64, "週票數變動率": "-63.01%", "銷售金額": 13575, "累計銷售票數": 1044, "累計銷售金額": 223960}, {"序號": 29, "國別地區": "美國", "中文片名": "A+瞎妹", "上映日期": "2020/03/20", "申請人": "車庫娛樂股份有限公司", "出品": "METRO-GOLDWYN-MAYER STUDIOS INC.", "上映院數": 6, "銷售票數": 43, "週票數變動率": "-85.57%", "銷售金額": 10150, "累計銷售票數": 2860, "累計銷售金額": 659811}, {"序號": 30, "國別地區": "德國", "中文片名": "不愛鋼琴師", "上映日期": "2020/03/20", "申請人": "光年映畫有限公司", "出品": "Beta Cinema GmbH", "上映院數": 1, "銷售票數": 42, "週票數變動率": "-59.22%", "銷售金額": 8760, "累計銷售票數": 804, "累計銷售金額": 172355}, {"序號": 31, "國別地區": "南韓", "中文片名": "神之一手：鬼手篇", "上映日期": "2020/03/20", "申請人": "車庫娛樂股份有限公司", "出品": "CJ ENM CO., LTD.", "上映院數": 5, "銷售票數": 24, "週票數變動率": "-77.14%", "銷售金額": 4990, "累計銷售票數": 2215, "累計銷售金額": 506076}, {"序號": 32, "國別地區": "美國", "中文片名": "最後晚安曲", "上映日期": "2020/03/20", "申請人": "本萃電影有限公司", "出品": "Westend Films Ltd.", "上映院數": 3, "銷售票數": 17, "週票數變動率": "-77.63%", "銷售金額": 3780, "累計銷售票數": 1660, "累計銷售金額": 356975}, {"序號": 33, "國別地區": "法國", "中文片名": "我出去醫下", "上映日期": "2020/03/20", "申請人": "原創娛樂股份有限公司", "出品": "Other Angle Pictures", "上映院數": 6, "銷售票數": 15, "週票數變動率": "-89.80%", "銷售金額": 3405, "累計銷售票數": 2446, "累計銷售金額": 550648}, {"序號": 34, "國別地區": "中華民國", "中文片名": "練愛iNG", "上映日期": "2020/03/13", "申請人": "威視股份有限公司", "出品": "量能文創股份有限公司##聚善美文創娛樂有限公司##遊戲橘子數位科技股份有限公司##恆動工作室##天鵬翱翔集團有限公司", "上映院數": 37, "銷售票數": 1069, "週票數變動率": "-65.90%", "銷售金額": 258674, "累計銷售票數": 37761, "累計銷售金額": 8800531}, {"序號": 35, "國別地區": "日本", "中文片名": "劇場版 不起眼女主角培育法 Fine", "上映日期": "2020/03/13", "申請人": "車庫娛樂股份有限公司", "出品": "ANIPLEX INC.", "上映院數": 15, "銷售票數": 876, "週票數變動率": "-35.78%", "銷售金額": 215531, "累計銷售票數": 19404, "累計銷售金額": 4739414}, {"序號": 36, "國別地區": "美國", "中文片名": "鋼鐵勳章", "上映日期": "2020/03/13", "申請人": "采昌國際多媒體股份有限公司", "出品": "Freeway Entertainment Kft", "上映院數": 7, "銷售票數": 53, "週票數變動率": "-83.01%", "銷售金額": 13183, "累計銷售票數": 12144, "累計銷售金額": 2743251}, {"序號": 37, "國別地區": "波蘭", "中文片名": "另類神父", "上映日期": "2020/03/13", "申請人": "聯影企業股份有限公司", "出品": "New Europe Film Sales", "上映院數": 1, "銷售票數": 28, "週票數變動率": "-69.23%", "銷售金額": 6140, "累計銷售票數": 1953, "累計銷售金額": 411702}, {"序號": 38, "國別地區": "南韓", "中文片名": "南山的部長們", "上映日期": "2020/03/13", "申請人": "車庫娛樂股份有限公司", "出品": "SHOWBOX CORP.", "上映院數": 1, "銷售票數": 10, "週票數變動率": "-76.19%", "銷售金額": 2375, "累計銷售票數": 2251, "累計銷售金額": 530924}, {"序號": 39, "國別地區": "泰國", "中文片名": "通靈少年2020", "上映日期": "2020/03/13", "申請人": "英屬維京群島商高捷全球開發有限公司 台灣分公司", "出品": "Sahamongkolfilm International Co., Ltd.", "上映院數": 2, "銷售票數": 6, "週票數變動率": "-82.35%", "銷售金額": 1100, "累計銷售票數": 4510, "累計銷售金額": 974268}, {"序號": 40, "國別地區": "美國", "中文片名": "血衛", "上映日期": "2020/03/12", "申請人": "薩摩亞商雄讚股份有限公司台灣分公司", "出品": "Bona Film Investment Company (Pacific RIM, USA)", "上映院數": 87, "銷售票數": 4494, "週票數變動率": "-66.30%", "銷售金額": 1092490, "累計銷售票數": 255152, "累計銷售金額": 60893694}, {"序號": 41, "國別地區": "南韓", "中文片名": "大畫特務", "上映日期": "2020/03/06", "申請人": "香港商甲上娛樂有限公司台灣分公司", "出品": "LOTTE CULTUREWORKS CO., LTD.", "上映院數": 16, "銷售票數": 109, "週票數變動率": "-77.62%", "銷售金額": 24320, "累計銷售票數": 51608, "累計銷售金額": 11805850}, {"序號": 42, "國別地區": "法國", "中文片名": "導演先生的完美假期", "上映日期": "2020/03/06", "申請人": "繁盛映畫有限公司", "出品": "Wild Bunch", "上映院數": 1, "銷售票數": 62, "週票數變動率": "-28.74%", "銷售金額": 13430, "累計銷售票數": 2833, "累計銷售金額": 603497}, {"序號": 43, "國別地區": "南韓", "中文片名": "明明會說話", "上映日期": "2020/03/06", "申請人": "英屬蓋曼群島商威望國際娛樂股份有限公司台灣分公司", "出品": "LittleBig Pictures", "上映院數": 3, "銷售票數": 24, "週票數變動率": "-74.47%", "銷售金額": 5180, "累計銷售票數": 20308, "累計銷售金額": 4490036}, {"序號": 44, "國別地區": "中華民國", "中文片名": "女鬼橋", "上映日期": "2020/02/27", "申請人": "星泰國際娛樂股份有限公司", "出品": "樂到家國際娛樂股份有限公司##天馬傳播事業有限公司##得藝文創國際股份有限公司##大慕影藝國際事業股份有限公司##氧氣電影有限公司##華映娛樂股份有限公司##海樂影業股份有限公司", "上映院數": 51, "銷售票數": 894, "週票數變動率": "-70.21%", "銷售金額": 208496, "累計銷售票數": 250379, "累計銷售金額": 57761803}, {"序號": 45, "國別地區": "美國", "中文片名": "隱形人", "上映日期": "2020/02/27", "申請人": "美商美國環球影片股份有限公司台灣分公司", "出品": "UNIVERSAL INTERNATIONAL FILMS LLC", "上映院數": 41, "銷售票數": 724, "週票數變動率": "-68.30%", "銷售金額": 183824, "累計銷售票數": 219630, "累計銷售金額": 52232848}, {"序號": 46, "國別地區": "日本", "中文片名": "鳴鳥不飛：烏雲密布", "上映日期": "2020/02/27", "申請人": "采昌國際多媒體股份有限公司", "出品": "SPO Entertainment Inc.", "上映院數": 11, "銷售票數": 133, "週票數變動率": "-74.86%", "銷售金額": 31645, "累計銷售票數": 28334, "累計銷售金額": 6894872}, {"序號": 47, "國別地區": "美國", "中文片名": "極地守護犬", "上映日期": "2020/02/27", "申請人": "博偉電影股份有限公司", "出品": "BUENA VISTA INTERNATIONAL, INC.", "上映院數": 8, "銷售票數": 56, "週票數變動率": "-70.53%", "銷售金額": 12305, "累計銷售票數": 71287, "累計銷售金額": 15989742}, {"序號": 48, "國別地區": "美國", "中文片名": "怨咒", "上映日期": "2020/02/27", "申請人": "美商台灣索尼影業發行股份有限公司台灣分公司", "出品": "SONY PICTURES RELEASING INTERNATIONAL CORPORATION.", "上映院數": 3, "銷售票數": 12, "週票數變動率": "-25.00%", "銷售金額": 2740, "累計銷售票數": 20850, "累計銷售金額": 4693762}, {"序號": 49, "國別地區": "瑞典", "中文片名": "千日千夜", "上映日期": "2020/02/27", "申請人": "東昊影業有限公司", "出品": "Roy Andersson Filmproduktion AB", "上映院數": 1, "銷售票數": 11, "週票數變動率": "-35.29%", "銷售金額": 2430, "累計銷售票數": 2568, "累計銷售金額": 560162}, {"序號": 50, "國別地區": "美國", "中文片名": "音速小子", "上映日期": "2020/02/21", "申請人": "美商美國派拉蒙影片股份有限公司台灣分公司", "出品": "PARAMOUNT PICTURES CORPORATION", "上映院數": 1, "銷售票數": 10, "週票數變動率": "-78.72%", "銷售金額": 2610, "累計銷售票數": 102388, "累計銷售金額": 24021720}, {"序號": 51, "國別地區": "西班牙", "中文片名": "絕命大平台", "上映日期": "2020/02/21", "申請人": "原創娛樂股份有限公司", "出品": "Latido Consorcio De Exportacion Del Cine Espanol SL", "上映院數": 1, "銷售票數": 4, "週票數變動率": "-71.43%", "銷售金額": 840, "累計銷售票數": 7269, "累計銷售金額": 1606463}, {"序號": 52, "國別地區": "日本", "中文片名": "愛情人形", "上映日期": "2020/02/14", "申請人": "天馬行空數位有限公司", "出品": "NIKKATSU CORPORATION", "上映院數": 1, "銷售票數": 12, "週票數變動率": "0.00%", "銷售金額": 1920, "累計銷售票數": 3365, "累計銷售金額": 762616}, {"序號": 53, "國別地區": "南韓", "中文片名": "超\"人\"氣動物園", "上映日期": "2020/02/14", "申請人": "車庫娛樂股份有限公司", "出品": "FINECUT CO., LTD.", "上映院數": 1, "銷售票數": 1, "週票數變動率": "-85.71%", "銷售金額": 200, "累計銷售票數": 139408, "累計銷售金額": 32522116}, {"序號": 54, "國別地區": "日本", "中文片名": "蜜蜂與遠雷", "上映日期": "2020/02/07", "申請人": "英屬蓋曼群島商威望國際娛樂股份有限公司台灣分公司", "出品": "Toho Co., Ltd", "上映院數": 1, "銷售票數": 12, "週票數變動率": "0.00%", "銷售金額": 1920, "累計銷售票數": 6413, "累計銷售金額": 1446943}, {"序號": 55, "國別地區": "美國", "中文片名": "我的寶貝男孩", "上映日期": "2020/02/07", "申請人": "美商台灣索尼影業發行股份有限公司台灣分公司", "出品": "SONY PICTURES RELEASING INTERNATIONAL CORPORATION.", "上映院數": 2, "銷售票數": 7, "週票數變動率": "-92.63%", "銷售金額": 410, "累計銷售票數": 1463, "累計銷售金額": 258229}, {"序號": 56, "國別地區": "日本", "中文片名": "王牌辯士", "上映日期": "2020/01/31", "申請人": "天馬行空數位有限公司", "出品": "TOEI COMPANY, LTD.", "上映院數": 2, "銷售票數": 13, "週票數變動率": "-63.89%", "銷售金額": 1890, "累計銷售票數": 1446, "累計銷售金額": 301525}, {"序號": 57, "國別地區": "美國", "中文片名": 1917, "上映日期": "2020/01/30", "申請人": "美商美國環球影片股份有限公司台灣分公司", "出品": "UNIVERSAL INTERNATIONAL FILMS LLC", "上映院數": 12, "銷售票數": 646, "週票數變動率": "-18.64%", "銷售金額": 211293, "累計銷售票數": 298585, "累計銷售金額": 73635161}, {"序號": 58, "國別地區": "南韓", "中文片名": "紅鞋公主與七矮人", "上映日期": "2020/01/30", "申請人": "可樂藝術文創股份有限公司", "出品": "FINECUT CO., LTD", "上映院數": 2, "銷售票數": 4, "週票數變動率": "400.00%", "銷售金額": 1040, "累計銷售票數": 22638, "累計銷售金額": 5230667}, {"序號": 59, "國別地區": "美國", "中文片名": "杜立德", "上映日期": "2020/01/23", "申請人": "美商美國環球影片股份有限公司台灣分公司", "出品": "UNIVERSAL INTERNATIONAL FILMS LLC", "上映院數": 3, "銷售票數": 216, "週票數變動率": "0.00%", "銷售金額": 20560, "累計銷售票數": 315966, "累計銷售金額": 75791482}, {"序號": 60, "國別地區": "香港", "中文片名": "肥龍過江", "上映日期": "2020/01/23", "申請人": "華映娛樂股份有限公司", "出品": "星王朝有限公司##上海博納文化傳媒有限公司##博納影業集團股份有限公司##上海新文化影業有限公司##電視廣播有限公司##太陽娛樂文化有限公司##上海杠杠影視文化有限公司##霍爾果斯環星影視傳媒有限公司##上海優創影視文化有限公司", "上映院數": 4, "銷售票數": 165, "週票數變動率": "-46.25%", "銷售金額": 12720, "累計銷售票數": 61821, "累計銷售金額": 13582882}, {"序號": 61, "國別地區": "中華民國", "中文片名": "你的情歌", "上映日期": "2020/01/23", "申請人": "香港商甲上娛樂有限公司台灣分公司", "出品": "奇想事企業有限公司##能率影業股份有限公司##香港商甲上娛樂有限公司台灣分公司 ##采昌國際多媒體股份有限公司  ##英屬維京群島商敦宜股份有限公司台灣分公司", "上映院數": 1, "銷售票數": 44, "週票數變動率": "0.00%", "銷售金額": 3400, "累計銷售票數": 82620, "累計銷售金額": 19371268}, {"序號": 62, "國別地區": "中華民國", "中文片名": "喜從天降", "上映日期": "2020/01/23", "申請人": "影一製作所股份有限公司", "出品": "影一製作所股份有限公司", "上映院數": 1, "銷售票數": 20, "週票數變動率": "-16.67%", "銷售金額": 2920, "累計銷售票數": 16059, "累計銷售金額": 3634919}, {"序號": 63, "國別地區": "俄羅斯", "中文片名": "岳父受死吧", "上映日期": "2020/01/23", "申請人": "麻吉砥加電影有限公司", "出品": "REEL SUSPECTS S.A.R.L.", "上映院數": 2, "銷售票數": 9, "週票數變動率": "0.00%", "銷售金額": 1855, "累計銷售票數": 305, "累計銷售金額": 69719}, {"序號": 64, "國別地區": "美國", "中文片名": "深海終劫站", "上映日期": "2020/01/22", "申請人": "博偉電影股份有限公司", "出品": "BUENA VISTA INTERNATIONAL, INC.", "上映院數": 5, "銷售票數": 441, "週票數變動率": "22.16%", "銷售金額": 32550, "累計銷售票數": 177865, "累計銷售金額": 40470730}, {"序號": 65, "國別地區": "美國", "中文片名": "變身特務", "上映日期": "2020/01/22", "申請人": "博偉電影股份有限公司", "出品": "BUENA VISTA INTERNATIONAL, INC.", "上映院數": 4, "銷售票數": 209, "週票數變動率": "127.17%", "銷售金額": 15450, "累計銷售票數": 181216, "累計銷售金額": 41366602}, {"序號": 66, "國別地區": "美國", "中文片名": "不完美的正義", "上映日期": "2020/01/17", "申請人": "美商華納兄弟（遠東）股份有限公司台灣分公司", "出品": "WARNER BROS. PICTURES INTERNATIONAL.", "上映院數": 4, "銷售票數": 223, "週票數變動率": "555.88%", "銷售金額": 15660, "累計銷售票數": 47260, "累計銷售金額": 10870917}, {"序號": 67, "國別地區": "丹麥", "中文片名": "在黑暗中漫舞：20週年數位修復版", "上映日期": "2020/01/17", "申請人": "光年映畫有限公司", "出品": "TRUSTNORDISK APS", "上映院數": 3, "銷售票數": 61, "週票數變動率": "5.17%", "銷售金額": 13400, "累計銷售票數": 4673, "累計銷售金額": 1037916}, {"序號": 68, "國別地區": "日本", "中文片名": "巧虎電影 英雄遊樂園", "上映日期": "2020/01/17", "申請人": "全民大劇團股份有限公司", "出品": "法人倍樂生株式會社", "上映院數": 17, "銷售票數": 14, "週票數變動率": "-79.71%", "銷售金額": 3430, "累計銷售票數": 17882, "累計銷售金額": 4222258}, {"序號": 69, "國別地區": "南韓", "中文片名": "青春催落去", "上映日期": "2020/01/17", "申請人": "車庫娛樂股份有限公司", "出品": "CONTENTS PANDA", "上映院數": 1, "銷售票數": 12, "週票數變動率": "-50.00%", "銷售金額": 1760, "累計銷售票數": 5495, "累計銷售金額": 1178100}, {"序號": 70, "國別地區": "美國", "中文片名": "絕地戰警FOR LIFE", "上映日期": "2020/01/16", "申請人": "美商台灣索尼影業發行股份有限公司台灣分公司", "出品": "SONY PICTURES RELEASING INTERNATIONAL CORPORATION.", "上映院數": 8, "銷售票數": 811, "週票數變動率": "-4.14%", "銷售金額": 62700, "累計銷售票數": 573337, "累計銷售金額": 136778945}, {"序號": 71, "國別地區": "西班牙", "中文片名": "逃出天堂島", "上映日期": "2020/01/10", "申請人": "海樂影業股份有限公司", "出品": "GEM ENTERTAINMENT KFT.", "上映院數": 1, "銷售票數": 15, "週票數變動率": "-76.19%", "銷售金額": 825, "累計銷售票數": 7572, "累計銷售金額": 1471547}, {"序號": 72, "國別地區": "法國", "中文片名": "星星知我心", "上映日期": "2020/01/10", "申請人": "采昌國際多媒體股份有限公司", "出品": "PATHE FILMS S.A.S", "上映院數": 1, "銷售票數": 6, "週票數變動率": "-75.00%", "銷售金額": 300, "累計銷售票數": 1581, "累計銷售金額": 301605}, {"序號": 73, "國別地區": "美國", "中文片名": "兔嘲男孩", "上映日期": "2020/01/03", "申請人": "博偉電影股份有限公司", "出品": "BUENA VISTA INTERNATIONAL, INC.", "上映院數": 5, "銷售票數": 479, "週票數變動率": "38.84%", "銷售金額": 38945, "累計銷售票數": 90258, "累計銷售金額": 21011383}, {"序號": 74, "國別地區": "印度", "中文片名": "真愛裁會贏", "上映日期": "2020/01/03", "申請人": "水元素文化傳媒有限公司", "出品": "YASH RAJ FILMS PRIVATE LIMITED", "上映院數": 2, "銷售票數": 45, "週票數變動率": "-66.67%", "銷售金額": 3325, "累計銷售票數": 7018, "累計銷售金額": 1339221}, {"序號": 75, "國別地區": "法國", "中文片名": "燃燒女子的畫像", "上映日期": "2019/12/20", "申請人": "東昊影業有限公司", "出品": "MK2 Films", "上映院數": 2, "銷售票數": 22, "週票數變動率": "22.22%", "銷售金額": 3420, "累計銷售票數": 15158, "累計銷售金額": 3341748}, {"序號": 76, "國別地區": "香港", "中文片名": "葉問4：完結篇", "上映日期": "2019/12/19", "申請人": "華映娛樂股份有限公司", "出品": "東方影業出品有限公司", "上映院數": 8, "銷售票數": 470, "週票數變動率": "-57.85%", "銷售金額": 40535, "累計銷售票數": 809055, "累計銷售金額": 185361223}, {"序號": 77, "國別地區": "加拿大", "中文片名": "8級警戒", "上映日期": "2019/12/13", "申請人": "車庫娛樂股份有限公司", "出品": "XYZ FILMS, LLC", "上映院數": 1, "銷售票數": 10, "週票數變動率": "-85.07%", "銷售金額": 800, "累計銷售票數": 5697, "累計銷售金額": 1142543}, {"序號": 78, "國別地區": "美國", "中文片名": "野蠻遊戲：全面晉級", "上映日期": "2019/12/04", "申請人": "美商台灣索尼影業發行股份有限公司台灣分公司", "出品": "SONY PICTURES RELEASING INTERNATIONAL CORPORATION.", "上映院數": 32, "銷售票數": 721, "週票數變動率": "-53.57%", "銷售金額": 145619, "累計銷售票數": 812176, "累計銷售金額": 190784492}, {"序號": 79, "國別地區": "英國", "中文片名": "茱莉小姐", "上映日期": "2019/12/04", "申請人": "威秀影城股份有限公司", "出品": "The Royal National Theatre", "上映院數": 1, "銷售票數": 6, "週票數變動率": "0.00%", "銷售金額": 4200, "累計銷售票數": 391, "累計銷售金額": 254180}, {"序號": 80, "國別地區": "英國", "中文片名": "哈利路亞！", "上映日期": "2019/12/04", "申請人": "威秀影城股份有限公司", "出品": "The Royal National Theatre", "上映院數": 4, "銷售票數": 6, "週票數變動率": "-50.00%", "銷售金額": 3920, "累計銷售票數": 347, "累計銷售金額": 220560}, {"序號": 81, "國別地區": "中華民國", "中文片名": "狂飆一夢", "上映日期": "2019/11/29", "申請人": "廖建華影像工作室", "出品": "廖建華影像工作室##一顆星工作室有限公司", "上映院數": 1, "銷售票數": 4, "週票數變動率": "-92.59%", "銷售金額": 970, "累計銷售票數": 1613, "累計銷售金額": 351514}, {"序號": 82, "國別地區": "西班牙/德國/荷蘭", "中文片名": "布紐爾 超現實人生", "上映日期": "2019/11/29", "申請人": "佳映娛樂國際股份有限公司", "出品": "LATIDO CONSORCIO DE EXPORTACION DEL CINE ESPANOL SL", "上映院數": 1, "銷售票數": 0, "週票數變動率": "0.00%", "銷售金額": 0, "累計銷售票數": 647, "累計銷售金額": 140610}, {"序號": 83, "國別地區": "美國", "中文片名": "賽道狂人", "上映日期": "2019/11/26", "申請人": "博偉電影股份有限公司", "出品": "BUENA VISTA INTERNATIONAL, INC.", "上映院數": 2, "銷售票數": 40, "週票數變動率": "-50.62%", "銷售金額": 3480, "累計銷售票數": 318567, "累計銷售金額": 77725858}, {"序號": 84, "國別地區": "美國", "中文片名": "冰雪奇緣2", "上映日期": "2019/11/21", "申請人": "台灣華特迪士尼股份有限公司", "出品": "BUENA VISTA INTERNATIONAL, INC.", "上映院數": 6, "銷售票數": 234, "週票數變動率": "-60.41%", "銷售金額": 19340, "累計銷售票數": 1453499, "累計銷售金額": 343867663}, {"序號": 85, "國別地區": "印度", "中文片名": "萬萬沒想到", "上映日期": "2019/11/15", "申請人": "英屬蓋曼群島商威望國際娛樂股份有限公司台灣分公司", "出品": "STAR INDIA PRIVATE LIMITED, Through its division, FOX STAR STUDIOS", "上映院數": 1, "銷售票數": 63, "週票數變動率": "0.00%", "銷售金額": 6550, "累計銷售票數": 50377, "累計銷售金額": 11056939}, {"序號": 86, "國別地區": "日本", "中文片名": "魔法少女伊莉雅 百變嘉年華", "上映日期": "2019/10/17", "申請人": "提恩傳媒實業有限公司", "出品": "KADOKAWA CORPORATION", "上映院數": 1, "銷售票數": 3, "週票數變動率": "-90.91%", "銷售金額": 720, "累計銷售票數": 1491, "累計銷售金額": 357961}, {"序號": 87, "國別地區": "日本", "中文片名": "普羅米亞", "上映日期": "2019/08/16", "申請人": "中影股份有限公司", "出品": "東寶株式會社", "上映院數": 4, "銷售票數": 32, "週票數變動率": "-70.91%", "銷售金額": 14590, "累計銷售票數": 79172, "累計銷售金額": 22352530}, {"序號": 88, "國別地區": "加拿大", "中文片名": "哈柏太空之旅 3D", "上映日期": "2019/02/04", "申請人": "國際電影事業有限公司", "出品": "IMAX Corporation", "上映院數": 1, "銷售票數": 0, "週票數變動率": "-100.00%", "銷售金額": 0, "累計銷售票數": 604, "累計銷售金額": 86710}, {"序號": 89, "國別地區": "加拿大", "中文片名": "深海獵奇 3D", "上映日期": "2019/02/03", "申請人": "國際電影事業有限公司", "出品": "IMAX Corporation", "上映院數": 1, "銷售票數": 0, "週票數變動率": "-100.00%", "銷售金額": 0, "累計銷售票數": 1198, "累計銷售金額": 149139}, {"序號": 90, "國別地區": "香港", "中文片名": "霸王別姬", "上映日期": "2018/12/14", "申請人": "能率影業股份有限公司", "出品": "湯臣(香港)電影有限公司", "上映院數": 12, "銷售票數": 158, "週票數變動率": "-79.10%", "銷售金額": 44033, "累計銷售票數": 52427, "累計銷售金額": 12484262}, {"序號": 91, "國別地區": "澳洲", "中文片名": "極限巔峰", "上映日期": "2018/11/03", "申請人": "佳映娛樂國際股份有限公司", "出品": "(英國)DOGWOOF", "上映院數": 1, "銷售票數": 0, "週票數變動率": "0.00%", "銷售金額": 0, "累計銷售票數": 523, "累計銷售金額": 123285}, {"序號": 92, "國別地區": "香港", "中文片名": "阿飛正傳", "上映日期": "2018/09/28", "申請人": "華映娛樂股份有限公司", "出品": "(英屬維京群島)EAST ASIA FILMS DISTRIBUTION LIMITED##(香港)ESUN.COM LIMITED", "上映院數": 2, "銷售票數": 255, "週票數變動率": "-30.71%", "銷售金額": 57650, "累計銷售票數": 6670, "累計銷售金額": 1537625}, {"序號": 93, "國別地區": "美國", "中文片名": "鬼店", "上映日期": "2018/09/28", "申請人": "美商華納兄弟(遠東)股份有限公司台灣分公司", "出品": "WARNER BROS. PICTURES INTERNATIONAL.", "上映院數": 1, "銷售票數": 2, "週票數變動率": "-33.33%", "銷售金額": 518, "累計銷售票數": 5587, "累計銷售金額": 1393809}, {"序號": 94, "國別地區": "美國", "中文片名": "侏羅紀世界:殞落國度", "上映日期": "2018/06/06", "申請人": "美商美國環球影片股份有限公司台灣分公司", "出品": "UNIVERSAL INTERNATIONAL FILMS LLC", "上映院數": 5, "銷售票數": 39, "週票數變動率": "-45.07%", "銷售金額": 7705, "累計銷售票數": 2554710, "累計銷售金額": 621695729}, {"序號": 95, "國別地區": "美國", "中文片名": "噤界", "上映日期": "2018/04/04", "申請人": "美商美國派拉蒙影片股份有限公司台灣分公司", "出品": "PARAMOUNT PICTURES CORPORATION", "上映院數": 4, "銷售票數": 11, "週票數變動率": "-60.71%", "銷售金額": 2330, "累計銷售票數": 315716, "累計銷售金額": 72409444}, {"序號": 96, "國別地區": "美國", "中文片名": "一級玩家", "上映日期": "2018/03/29", "申請人": "美商華納兄弟（遠東）股份有限公司台灣分公司", "出品": "WARNER BROS. PICTURES INTERNATIONAL.", "上映院數": 5, "銷售票數": 213, "週票數變動率": "0.00%", "銷售金額": 105850, "累計銷售票數": 1416521, "累計銷售金額": 362149303}, {"序號": 97, "國別地區": "美國", "中文片名": "樂來越愛你", "上映日期": "2016/12/09", "申請人": "英屬蓋曼群島商威望國際娛樂股份有限公司台灣分公司", "出品": "(英國)LIONS GATE INTERNATIONAL (UK) LIMITED", "上映院數": 17, "銷售票數": 415, "週票數變動率": "0.00%", "銷售金額": 110412, "累計銷售票數": 561368, "累計銷售金額": 132732054}, {"序號": 98, "國別地區": "義大利", "中文片名": "完美陌生人", "上映日期": "2016/10/21", "申請人": "海鵬影業有限公司", "出品": "TRUE COLOURS GLORIOUS FILMS S.R.L", "上映院數": 2, "銷售票數": 58, "週票數變動率": "0.00%", "銷售金額": 11150, "累計銷售票數": 12290, "累計銷售金額": 2502990}, {"序號": 99, "國別地區": "日本", "中文片名": "情書", "上映日期": "2016/09/09", "申請人": "可樂藝術文創股份有限公司", "出品": "FORTISSIMO AMSTERDAM B.V", "上映院數": 2, "銷售票數": 9, "週票數變動率": "-40.00%", "銷售金額": 1870, "累計銷售票數": 13738, "累計銷售金額": 3100543}, {"序號": 100, "國別地區": "日本", "中文片名": "比海還深", "上映日期": "2016/09/02", "申請人": "傳影互動股份有限公司", "出品": "GAGA CORPORATION", "上映院數": 1, "銷售票數": 16, "週票數變動率": "0.00%", "銷售金額": 3430, "累計銷售票數": 22147, "累計銷售金額": 4906642}, {"序號": 101, "國別地區": "南韓", "中文片名": "下女的誘惑", "上映日期": "2016/06/24", "申請人": "英屬蓋曼群島商威望國際娛樂股份有限公司台灣分公司", "出品": "CJ E&M CORPORATION", "上映院數": 3, "銷售票數": 136, "週票數變動率": "0.00%", "銷售金額": 32085, "累計銷售票數": 32539, "累計銷售金額": 6775730}, {"序號": 102, "國別地區": "美國", "中文片名": "出神入化2", "上映日期": "2016/06/08", "申請人": "英屬維京群島商高捷全球開發有限公司台灣分公司", "出品": "SUMMIT ENTERTAINMENT, LLC", "上映院數": 4, "銷售票數": 7, "週票數變動率": "-58.82%", "銷售金額": 1510, "累計銷售票數": 939601, "累計銷售金額": 223346779}, {"序號": 103, "國別地區": "英國", "中文片名": "李爾王", "上映日期": "2016/04/23", "申請人": "威秀影城股份有限公司", "出品": "THE ROYAL NATIONAL THEATRE", "上映院數": 1, "銷售票數": 7, "週票數變動率": "0.00%", "銷售金額": 4760, "累計銷售票數": 1498, "累計銷售金額": 1040780}, {"序號": 104, "國別地區": "日本", "中文片名": "橫山家之味", "上映日期": "2009/04/03", "申請人": "傳影互動股份有限公司", "出品": "(法國) CELLULOID DREAMS SAS", "上映院數": 1, "銷售票數": 27, "週票數變動率": "0.00%", "銷售金額": 5465, "累計銷售票數": 1243, "累計銷售金額": 252400}, {"序號": 105, "國別地區": "美國", "中文片名": "刺激1995", "上映日期": "1995/03/10", "申請人": "美商華納兄弟（遠東）股份有限公司台灣分公司", "出品": "WARNER BROS. PICTURES INTERNATIONAL.", "上映院數": 31, "銷售票數": 1133, "週票數變動率": "-57.05%", "銷售金額": 271505, "累計銷售票數": 22159, "累計銷售金額": 5406655}, {"序號": 106, "國別地區": "美國", "中文片名": "第六感生死戀", "上映日期": "1990/12/15", "申請人": "捷傑有限公司", "出品": "United International Pictures", "上映院數": 24, "銷售票數": 234, "週票數變動率": "-70.90%", "銷售金額": 54068, "累計銷售票數": 1922, "累計銷售金額": 442773}]