[{"序號": 1, "國別地區": "俄羅斯", "中文片名": "黑暗戰域", "上映日期": "2020/05/08", "申請人": "車庫娛樂股份有限公司", "出品": "CENTRAL PARTNERSHIP SALES HOUSE", "上映院數": 53, "銷售票數": 4916, "週票數變動率": "-7.72%", "銷售金額": 1140519, "累計銷售票數": 10243, "累計銷售金額": 2368202}, {"序號": 2, "國別地區": "日本", "中文片名": "劇場版 白箱", "上映日期": "2020/05/08", "申請人": "車庫娛樂股份有限公司", "出品": "HAKUHODO DY MUSIC & PICTURES INC.", "上映院數": 22, "銷售票數": 3221, "週票數變動率": "10.01%", "銷售金額": 802631, "累計銷售票數": 6149, "累計銷售金額": 1535248}, {"序號": 3, "國別地區": "香港", "中文片名": "金都", "上映日期": "2020/05/08", "申請人": "采昌國際多媒體股份有限公司", "出品": "金都電影製作有限公司My Prince Edward Film Production Limited", "上映院數": 32, "銷售票數": 1615, "週票數變動率": "38.27%", "銷售金額": 355089, "累計銷售票數": 2783, "累計銷售金額": 608045}, {"序號": 4, "國別地區": "法國", "中文片名": "陪你玩最大", "上映日期": "2020/05/08", "申請人": "英屬蓋曼群島商威望國際娛樂股份有限公司台灣分公司", "出品": "Pathé Films S.A.S", "上映院數": 36, "銷售票數": 1214, "週票數變動率": "18.44%", "銷售金額": 272486, "累計銷售票數": 2239, "累計銷售金額": 497807}, {"序號": 5, "國別地區": "日本", "中文片名": "初戀", "上映日期": "2020/05/08", "申請人": "車庫娛樂股份有限公司", "出品": "TOEI COMPANY, LTD.", "上映院數": 38, "銷售票數": 978, "週票數變動率": "17.69%", "銷售金額": 219943, "累計銷售票數": 1809, "累計銷售金額": 407511}, {"序號": 6, "國別地區": "美國", "中文片名": "觸不到的愛", "上映日期": "2020/05/08", "申請人": "威視股份有限公司", "出品": "LOTUS MEDIA LLC", "上映院數": 12, "銷售票數": 589, "週票數變動率": "15.26%", "銷售金額": 143300, "累計銷售票數": 1100, "累計銷售金額": 272225}, {"序號": 7, "國別地區": "中華民國", "中文片名": "老娘就要這麼活", "上映日期": "2020/05/08", "申請人": "春暉映像有限公司", "出品": "萊思捷有限公司", "上映院數": 19, "銷售票數": 319, "週票數變動率": "-5.06%", "銷售金額": 70900, "累計銷售票數": 655, "累計銷售金額": 147136}, {"序號": 8, "國別地區": "德國", "中文片名": "閉嘴！彈琴", "上映日期": "2020/05/08", "申請人": "前景娛樂有限公司", "出品": "CHARADES", "上映院數": 13, "銷售票數": 222, "週票數變動率": "48.99%", "銷售金額": 49508, "累計銷售票數": 371, "累計銷售金額": 81506}, {"序號": 9, "國別地區": "中國大陸", "中文片名": "素人特工", "上映日期": "2020/05/08", "申請人": "馬棋朵數位影像製作有限公司", "出品": "新麗傳媒集團有限公司 \t ##新麗國際傳媒有限公司 \t ##上海淘票票影視文化有限公司 \t ##華夏電影發行有限責任公司 \t ##英皇影業有限公司 \t ##原生映画有限公司 \t ##萬達影視傳媒有限公司 \t ##優酷電影有限公司 \t ##北京集智映像影視文化有限公司 \t ##引力影視投資有限公司 \t ##引力影視國際有限公司", "上映院數": 2, "銷售票數": 134, "週票數變動率": "-32.66%", "銷售金額": 29725, "累計銷售票數": 333, "累計銷售金額": 74500}, {"序號": 10, "國別地區": "美國", "中文片名": "壞教育", "上映日期": "2020/04/30", "申請人": "香港商甲上娛樂有限公司台灣分公司", "出品": "Jellyfish Bloom International, LLC##Sight Unseen Pictures LLC", "上映院數": 63, "銷售票數": 6349, "週票數變動率": "-27.98%", "銷售金額": 1510432, "累計銷售票數": 25281, "累計銷售金額": 5942420}, {"序號": 11, "國別地區": "泰國", "中文片名": "見鬼的戀愛季節", "上映日期": "2020/04/30", "申請人": "英屬維京群島商高捷全球開發有限公司 台灣分公司", "出品": "Sahamongkolfilm International Co.,Ltd.", "上映院數": 62, "銷售票數": 5753, "週票數變動率": "-20.22%", "銷售金額": 1292190, "累計銷售票數": 19930, "累計銷售金額": 4475275}, {"序號": 12, "國別地區": "美國", "中文片名": "鎖命佈局", "上映日期": "2020/04/30", "申請人": "采昌國際多媒體股份有限公司", "出品": "Atrium Productions Kft.", "上映院數": 70, "銷售票數": 4426, "週票數變動率": "-29.65%", "銷售金額": 1048565, "累計銷售票數": 17036, "累計銷售金額": 3955138}, {"序號": 13, "國別地區": "德國", "中文片名": "抽屍剝繭", "上映日期": "2020/04/30", "申請人": "海鵬影業有限公司", "出品": "GLOBAL SCREEN GMBH", "上映院數": 56, "銷售票數": 3039, "週票數變動率": "-27.33%", "銷售金額": 675330, "累計銷售票數": 10996, "累計銷售金額": 2441696}, {"序號": 14, "國別地區": "南韓", "中文片名": "流感", "上映日期": "2020/04/30", "申請人": "車庫娛樂股份有限公司", "出品": "RELAY MOTION KFT.", "上映院數": 35, "銷售票數": 2046, "週票數變動率": "-39.93%", "銷售金額": 470441, "累計銷售票數": 9164, "累計銷售金額": 2112769}, {"序號": 15, "國別地區": "巴拉圭", "中文片名": "現屍報", "上映日期": "2020/04/30", "申請人": "可樂藝術文創股份有限公司", "出品": "ATRIUM Productions Kft.", "上映院數": 49, "銷售票數": 1017, "週票數變動率": "-41.62%", "銷售金額": 224154, "累計銷售票數": 5109, "累計銷售金額": 1134586}, {"序號": 16, "國別地區": "英國", "中文片名": "監禁100呎", "上映日期": "2020/04/30", "申請人": "車庫娛樂股份有限公司", "出品": "ALTITUDE FILM SALES LIMITED", "上映院數": 27, "銷售票數": 217, "週票數變動率": "-73.01%", "銷售金額": 49791, "累計銷售票數": 1923, "累計銷售金額": 437208}, {"序號": 17, "國別地區": "南韓", "中文片名": "正在相愛嗎?", "上映日期": "2020/04/30", "申請人": "海樂影業股份有限公司", "出品": "Lian Contents Co., Ltd.", "上映院數": 30, "銷售票數": 149, "週票數變動率": "-73.72%", "銷售金額": 32341, "累計銷售票數": 1433, "累計銷售金額": 299202}, {"序號": 18, "國別地區": "義大利", "中文片名": "如果我擁抱你請不要害怕", "上映日期": "2020/04/30", "申請人": "聯影企業股份有限公司", "出品": "Rai Com S.p.A.", "上映院數": 12, "銷售票數": 126, "週票數變動率": "-59.22%", "銷售金額": 25760, "累計銷售票數": 802, "累計銷售金額": 170489}, {"序號": 19, "國別地區": "美國", "中文片名": "帕華洛帝：世紀男高音", "上映日期": "2020/04/30", "申請人": "車庫娛樂股份有限公司", "出品": "POLYGRAM ENTERTAINMENT, LLC", "上映院數": 7, "銷售票數": 120, "週票數變動率": "-61.90%", "銷售金額": 23990, "累計銷售票數": 707, "累計銷售金額": 143452}, {"序號": 20, "國別地區": "法國", "中文片名": "熊熊大作戰", "上映日期": "2020/04/30", "申請人": "英屬蓋曼群島商威望國際娛樂股份有限公司台灣分公司", "出品": "Pathé Films S.A.S", "上映院數": 10, "銷售票數": 83, "週票數變動率": "-68.80%", "銷售金額": 19055, "累計銷售票數": 701, "累計銷售金額": 160123}, {"序號": 21, "國別地區": "義大利", "中文片名": "聽教父的話", "上映日期": "2020/04/30", "申請人": "東昊影業有限公司", "出品": "TRUE COLOURS GLORIOUS FILMS srl", "上映院數": 4, "銷售票數": 39, "週票數變動率": "-75.63%", "銷售金額": 7885, "累計銷售票數": 321, "累計銷售金額": 64850}, {"序號": 22, "國別地區": "日本", "中文片名": "數碼寶貝 LAST EVOLUTION 絆", "上映日期": "2020/04/24", "申請人": "曼迪傳播有限公司", "出品": "TOEI ANIMATION CO., LTD.", "上映院數": 16, "銷售票數": 16778, "週票數變動率": "-21.43%", "銷售金額": 4295992, "累計銷售票數": 68463, "累計銷售金額": 17411997}, {"序號": 23, "國別地區": "法國", "中文片名": "美好拾光公司", "上映日期": "2020/04/24", "申請人": "英屬蓋曼群島商威望國際娛樂股份有限公司台灣分公司", "出品": "Pathe Films S.A.S.", "上映院數": 25, "銷售票數": 1695, "週票數變動率": "-11.67%", "銷售金額": 398013, "累計銷售票數": 8091, "累計銷售金額": 1867674}, {"序號": 24, "國別地區": "印尼", "中文片名": "蜈蚣降", "上映日期": "2020/04/24", "申請人": "車庫娛樂股份有限公司", "出品": "RELAY MOTION KFT.", "上映院數": 36, "銷售票數": 1607, "週票數變動率": "-36.66%", "銷售金額": 378692, "累計銷售票數": 14063, "累計銷售金額": 3280150}, {"序號": 25, "國別地區": "西班牙", "中文片名": "搭火車旅行好吃驚", "上映日期": "2020/04/24", "申請人": "天馬行空數位有限公司", "出品": "SEVILLE PICTURES INC.", "上映院數": 9, "銷售票數": 337, "週票數變動率": "-29.20%", "銷售金額": 73023, "累計銷售票數": 2533, "累計銷售金額": 555735}, {"序號": 26, "國別地區": "日本", "中文片名": "假面騎士－ 令和時代的開端", "上映日期": "2020/04/24", "申請人": "木棉花國際股份有限公司", "出品": "TOEI COMPANY, LTD.", "上映院數": 13, "銷售票數": 275, "週票數變動率": "-55.28%", "銷售金額": 67040, "累計銷售票數": 4251, "累計銷售金額": 1029506}, {"序號": 27, "國別地區": "南韓", "中文片名": "長沙里之戰：被遺忘的英雄", "上映日期": "2020/04/24", "申請人": "車庫娛樂股份有限公司", "出品": "FINECUT CO., LTD.", "上映院數": 20, "銷售票數": 240, "週票數變動率": "-62.44%", "銷售金額": 56156, "累計銷售票數": 6246, "累計銷售金額": 1440581}, {"序號": 28, "國別地區": "西班牙", "中文片名": "靈異孤兒院", "上映日期": "2020/04/24", "申請人": "車庫娛樂股份有限公司", "出品": "(法國)WILD BUNCH", "上映院數": 8, "銷售票數": 127, "週票數變動率": "-52.96%", "銷售金額": 29887, "累計銷售票數": 1661, "累計銷售金額": 391382}, {"序號": 29, "國別地區": "法國", "中文片名": "吞噬", "上映日期": "2020/04/24", "申請人": "本萃電影有限公司", "出品": "CHARADES", "上映院數": 6, "銷售票數": 110, "週票數變動率": "-43.88%", "銷售金額": 24300, "累計銷售票數": 1916, "累計銷售金額": 442013}, {"序號": 30, "國別地區": "匈牙利", "中文片名": "日暮", "上映日期": "2020/04/24", "申請人": "前景娛樂有限公司", "出品": "Playtime", "上映院數": 4, "銷售票數": 81, "週票數變動率": "-53.98%", "銷售金額": 16755, "累計銷售票數": 970, "累計銷售金額": 199440}, {"序號": 31, "國別地區": "德國", "中文片名": "無聲革命", "上映日期": "2020/04/24", "申請人": "捷傑有限公司", "出品": "STUDIOCANAL", "上映院數": 5, "銷售票數": 74, "週票數變動率": "-64.25%", "銷售金額": 15580, "累計銷售票數": 1150, "累計銷售金額": 249274}, {"序號": 32, "國別地區": "法國", "中文片名": "緣來想見妳", "上映日期": "2020/04/24", "申請人": "采昌國際多媒體股份有限公司", "出品": "GAUMONT S.A.", "上映院數": 10, "銷售票數": 54, "週票數變動率": "-71.73%", "銷售金額": 11525, "累計銷售票數": 2100, "累計銷售金額": 458439}, {"序號": 33, "國別地區": "馬來西亞", "中文片名": "這一刻，想見你", "上映日期": "2020/04/24", "申請人": "滿滿額娛樂股份有限公司", "出品": "mm2 Entertainment##邁進國際投資控股有限公司Max Capital Management Holding Ltd.##硯石(廈門)文化傳媒有限公司 Inkstone (Xiamen) Culture Media Co., Ltd.", "上映院數": 1, "銷售票數": 11, "週票數變動率": "-84.51%", "銷售金額": 2785, "累計銷售票數": 1100, "累計銷售金額": 262266}, {"序號": 34, "國別地區": "日本", "中文片名": "二階堂家物語", "上映日期": "2020/04/24", "申請人": "華映娛樂股份有限公司", "出品": "LDH Japan##英皇影業有限公司##Nara International Film Festival", "上映院數": 2, "銷售票數": 11, "週票數變動率": "-72.50%", "銷售金額": 2000, "累計銷售票數": 615, "累計銷售金額": 127005}, {"序號": 35, "國別地區": "日本", "中文片名": "惡之華", "上映日期": "2020/04/24", "申請人": "原創娛樂股份有限公司", "出品": "NIKKATSU Corporation", "上映院數": 2, "銷售票數": 4, "週票數變動率": "-90.00%", "銷售金額": 935, "累計銷售票數": 637, "累計銷售金額": 146061}, {"序號": 36, "國別地區": "英國", "中文片名": "一報還一報", "上映日期": "2020/04/20", "申請人": "威秀影城股份有限公司", "出品": "Trafalgar Releasing Limited", "上映院數": 5, "銷售票數": 36, "週票數變動率": "620.00%", "銷售金額": 24200, "累計銷售票數": 54, "累計銷售金額": 36640}, {"序號": 37, "國別地區": "日本", "中文片名": "知道天空有多藍的人啊", "上映日期": "2020/04/17", "申請人": "車庫娛樂股份有限公司", "出品": "ANIPLEX INC.", "上映院數": 21, "銷售票數": 813, "週票數變動率": "-10.76%", "銷售金額": 204491, "累計銷售票數": 10437, "累計銷售金額": 2514908}, {"序號": 38, "國別地區": "俄羅斯", "中文片名": "末日異戰", "上映日期": "2020/04/17", "申請人": "車庫娛樂股份有限公司", "出品": "ART PICTURES DISTRIBUTION LLC", "上映院數": 29, "銷售票數": 545, "週票數變動率": "-50.77%", "銷售金額": 127720, "累計銷售票數": 19186, "累計銷售金額": 4484999}, {"序號": 39, "國別地區": "丹麥", "中文片名": "築夢奇蹟", "上映日期": "2020/04/17", "申請人": "木棉花國際股份有限公司", "出品": "SOLA MEDIA GmbH", "上映院數": 16, "銷售票數": 248, "週票數變動率": "-0.80%", "銷售金額": 53422, "累計銷售票數": 3932, "累計銷售金額": 864376}, {"序號": 40, "國別地區": "英國", "中文片名": "居禮夫人：放射永恆", "上映日期": "2020/04/17", "申請人": "英屬蓋曼群島商威望國際娛樂股份有限公司台灣分公司", "出品": "Studiocanal", "上映院數": 10, "銷售票數": 148, "週票數變動率": "-39.09%", "銷售金額": 32545, "累計銷售票數": 4364, "累計銷售金額": 976597}, {"序號": 41, "國別地區": "澳洲", "中文片名": "鑰命監獄", "上映日期": "2020/04/17", "申請人": "天馬行空數位有限公司", "出品": "IPA-International Production Associates,Inc", "上映院數": 12, "銷售票數": 127, "週票數變動率": "-64.43%", "銷售金額": 31161, "累計銷售票數": 5819, "累計銷售金額": 1385486}, {"序號": 42, "國別地區": "俄羅斯", "中文片名": "罪：米開朗基羅", "上映日期": "2020/04/17", "申請人": "佳映娛樂國際股份有限公司", "出品": "ARRI Media GmbH", "上映院數": 4, "銷售票數": 101, "週票數變動率": "-35.26%", "銷售金額": 21095, "累計銷售票數": 1547, "累計銷售金額": 322650}, {"序號": 43, "國別地區": "日本", "中文片名": "星光王子 星光時尚秀 BEST10", "上映日期": "2020/04/17", "申請人": "提恩傳媒實業有限公司", "出品": "Avex Pictures", "上映院數": 7, "銷售票數": 63, "週票數變動率": "-8.70%", "銷售金額": 15151, "累計銷售票數": 1180, "累計銷售金額": 273742}, {"序號": 44, "國別地區": "法國", "中文片名": "戀愛倒帶中", "上映日期": "2020/04/17", "申請人": "光年映畫有限公司", "出品": "CHARADES", "上映院數": 3, "銷售票數": 35, "週票數變動率": "-47.76%", "銷售金額": 7535, "累計銷售票數": 1642, "累計銷售金額": 357214}, {"序號": 45, "國別地區": "日本", "中文片名": "浪人47愁錢中", "上映日期": "2020/04/17", "申請人": "可樂藝術文創股份有限公司", "出品": "MCIP Holdings Co., LTD.", "上映院數": 2, "銷售票數": 12, "週票數變動率": "33.33%", "銷售金額": 2890, "累計銷售票數": 1262, "累計銷售金額": 281547}, {"序號": 46, "國別地區": "印度", "中文片名": "我的粉紅人生", "上映日期": "2020/04/17", "申請人": "車庫娛樂股份有限公司", "出品": "AUTUMN SUN COMPANY LTD.", "上映院數": 1, "銷售票數": 6, "週票數變動率": "-50.00%", "銷售金額": 1440, "累計銷售票數": 418, "累計銷售金額": 84190}, {"序號": 47, "國別地區": "日本", "中文片名": "來自深淵 深沉靈魂的黎明", "上映日期": "2020/04/10", "申請人": "向洋影業有限公司", "出品": "株式会社KADOKAWA", "上映院數": 17, "銷售票數": 1918, "週票數變動率": "51.02%", "銷售金額": 677398, "累計銷售票數": 19994, "累計銷售金額": 5214338}, {"序號": 48, "國別地區": "法國", "中文片名": "真實", "上映日期": "2020/04/10", "申請人": "車庫娛樂股份有限公司", "出品": "GAGA CORPORATION", "上映院數": 1, "銷售票數": 74, "週票數變動率": "-5.13%", "銷售金額": 15225, "累計銷售票數": 3492, "累計銷售金額": 754661}, {"序號": 49, "國別地區": "美國", "中文片名": "女聲我最美", "上映日期": "2020/04/10", "申請人": "采昌國際多媒體股份有限公司", "出品": "EMBANKMENT FILMS LIMITED", "上映院數": 1, "銷售票數": 3, "週票數變動率": "0.00%", "銷售金額": 620, "累計銷售票數": 2161, "累計銷售金額": 462831}, {"序號": 50, "國別地區": "南韓", "中文片名": "政客誠實中", "上映日期": "2020/04/10", "申請人": "車庫娛樂股份有限公司", "出品": "CONTENTS PANDA", "上映院數": 1, "銷售票數": 2, "週票數變動率": "-89.47%", "銷售金額": 480, "累計銷售票數": 6978, "累計銷售金額": 1600285}, {"序號": 51, "國別地區": "美國", "中文片名": "搞鬼", "上映日期": "2020/04/09", "申請人": "香港商甲上娛樂有限公司台灣分公司", "出品": "BANKSIDE FILMS LTD", "上映院數": 33, "銷售票數": 500, "週票數變動率": "-39.32%", "銷售金額": 111704, "累計銷售票數": 24271, "累計銷售金額": 5576613}, {"序號": 52, "國別地區": "英國", "中文片名": "馴悍記", "上映日期": "2020/04/08", "申請人": "威秀影城股份有限公司", "出品": "Trafalgar Releasing Limited", "上映院數": 4, "銷售票數": 13, "週票數變動率": "-55.17%", "銷售金額": 9440, "累計銷售票數": 57, "累計銷售金額": 39680}, {"序號": 53, "國別地區": "日本", "中文片名": "我的英雄學院劇場版：英雄新世紀", "上映日期": "2020/04/01", "申請人": "薩摩亞商羚邦(亞洲)有限公司台灣分公司", "出品": "Toho Co., Ltd.", "上映院數": 46, "銷售票數": 1853, "週票數變動率": "-5.51%", "銷售金額": 478058, "累計銷售票數": 58405, "累計銷售金額": 14273824}, {"序號": 54, "國別地區": "日本", "中文片名": "犬鳴村", "上映日期": "2020/04/01", "申請人": "車庫娛樂股份有限公司", "出品": "TOEI COMPANY, LTD.", "上映院數": 11, "銷售票數": 142, "週票數變動率": "-37.72%", "銷售金額": 31889, "累計銷售票數": 31402, "累計銷售金額": 7369760}, {"序號": 55, "國別地區": "墨西哥", "中文片名": "羊男的迷宮", "上映日期": "2020/04/01", "申請人": "車庫娛樂股份有限公司", "出品": "(法國)WILD BUNCH", "上映院數": 2, "銷售票數": 92, "週票數變動率": "31.43%", "銷售金額": 24150, "累計銷售票數": 4095, "累計銷售金額": 961652}, {"序號": 56, "國別地區": "美國", "中文片名": "間諜速成班", "上映日期": "2020/04/01", "申請人": "英屬蓋曼群島商威望國際娛樂股份有限公司台灣分公司", "出品": "STX Productions, LLC", "上映院數": 10, "銷售票數": 78, "週票數變動率": "-45.07%", "銷售金額": 16725, "累計銷售票數": 20172, "累計銷售金額": 4545922}, {"序號": 57, "國別地區": "英國", "中文片名": "亨利五世", "上映日期": "2020/04/01", "申請人": "威秀影城股份有限公司", "出品": "SHAKESPEARE'S GLOBE TRUST", "上映院數": 1, "銷售票數": 21, "週票數變動率": "0.00%", "銷售金額": 15080, "累計銷售票數": 60, "累計銷售金額": 41160}, {"序號": 58, "國別地區": "美國", "中文片名": "魔髮精靈唱遊世界", "上映日期": "2020/04/01", "申請人": "美商美國環球影片股份有限公司台灣分公司", "出品": "UNIVERSAL INTERNATIONAL FILMS LLC", "上映院數": 3, "銷售票數": 38, "週票數變動率": "31.03%", "銷售金額": 8670, "累計銷售票數": 10816, "累計銷售金額": 2466477}, {"序號": 59, "國別地區": "日本", "中文片名": "火口的二人", "上映日期": "2020/04/01", "申請人": "采昌國際多媒體股份有限公司", "出品": "Hakuhodo DY music & pictures Inc.", "上映院數": 1, "銷售票數": 11, "週票數變動率": "-15.38%", "銷售金額": 2890, "累計銷售票數": 3878, "累計銷售金額": 891520}, {"序號": 60, "國別地區": "美國", "中文片名": "託陰2：布拉姆回來了", "上映日期": "2020/03/27", "申請人": "英屬蓋曼群島商威望國際娛樂股份有限公司台灣分公司", "出品": "STX Productions, LLC", "上映院數": 3, "銷售票數": 19, "週票數變動率": "-62.75%", "銷售金額": 3610, "累計銷售票數": 18040, "累計銷售金額": 4091597}, {"序號": 61, "國別地區": "美國", "中文片名": "絕命直播", "上映日期": "2020/03/27", "申請人": "香港商甲上娛樂有限公司台灣分公司", "出品": "Live Movie, LLC", "上映院數": 3, "銷售票數": 12, "週票數變動率": "-33.33%", "銷售金額": 2430, "累計銷售票數": 16245, "累計銷售金額": 3688502}, {"序號": 62, "國別地區": "日本", "中文片名": "記憶屋", "上映日期": "2020/03/27", "申請人": "天馬行空數位有限公司", "出品": "Shochiku Co., Ltd", "上映院數": 1, "銷售票數": 13, "週票數變動率": "0.00%", "銷售金額": 2080, "累計銷售票數": 1794, "累計銷售金額": 411066}, {"序號": 63, "國別地區": "日本", "中文片名": "Re：從零開始的異世界生活-外傳篇章電影", "上映日期": "2020/03/27", "申請人": "木棉花國際股份有限公司", "出品": "KADOKAWA SHOTEN CO., LTD.", "上映院數": 1, "銷售票數": 6, "週票數變動率": "-76.92%", "銷售金額": 1740, "累計銷售票數": 13055, "累計銷售金額": 2902066}, {"序號": 64, "國別地區": "南韓", "中文片名": "抓住救命稻草的野獸們", "上映日期": "2020/03/27", "申請人": "薩摩亞商雄讚股份有限公司台灣分公司", "出品": "M-Line Distribution Corportation", "上映院數": 2, "銷售票數": 4, "週票數變動率": "-71.43%", "銷售金額": 700, "累計銷售票數": 15240, "累計銷售金額": 3409552}, {"序號": 65, "國別地區": "美國", "中文片名": "無聲救援", "上映日期": "2020/03/27", "申請人": "車庫娛樂股份有限公司", "出品": "ROCKET SCIENCE INDUSTRIES LTD.", "上映院數": 1, "銷售票數": 1, "週票數變動率": "100.00%", "銷售金額": 280, "累計銷售票數": 6998, "累計銷售金額": 1602375}, {"序號": 66, "國別地區": "中華民國", "中文片名": "我不流行二十年", "上映日期": "2020/03/20", "申請人": "韶光電影有限公司", "出品": "角頭文化事業股份有限公司", "上映院數": 3, "銷售票數": 52, "週票數變動率": "-22.39%", "銷售金額": 15468, "累計銷售票數": 1579, "累計銷售金額": 381686}, {"序號": 67, "國別地區": "法國", "中文片名": "我出去醫下", "上映日期": "2020/03/20", "申請人": "原創娛樂股份有限公司", "出品": "Other Angle Pictures", "上映院數": 2, "銷售票數": 77, "週票數變動率": "0.00%", "銷售金額": 6840, "累計銷售票數": 2523, "累計銷售金額": 557488}, {"序號": 68, "國別地區": "日本", "中文片名": "劇場版 不起眼女主角培育法 Fine", "上映日期": "2020/03/13", "申請人": "車庫娛樂股份有限公司", "出品": "ANIPLEX INC.", "上映院數": 5, "銷售票數": 185, "週票數變動率": "11.45%", "銷售金額": 47514, "累計銷售票數": 20734, "累計銷售金額": 5070924}, {"序號": 69, "國別地區": "中華民國", "中文片名": "練愛iNG", "上映日期": "2020/03/13", "申請人": "威視股份有限公司", "出品": "量能文創股份有限公司##聚善美文創娛樂有限公司##遊戲橘子數位科技股份有限公司##恆動工作室##天鵬翱翔集團有限公司", "上映院數": 2, "銷售票數": 20, "週票數變動率": "-39.39%", "銷售金額": 4800, "累計銷售票數": 38802, "累計銷售金額": 9048299}, {"序號": 70, "國別地區": "英國", "中文片名": "複製柔伊", "上映日期": "2020/03/13", "申請人": "天馬行空數位有限公司", "出品": "PROTAGONIST PICTURES LIMITED", "上映院數": 1, "銷售票數": 19, "週票數變動率": "72.73%", "銷售金額": 2880, "累計銷售票數": 420, "累計銷售金額": 85030}, {"序號": 71, "國別地區": "美國", "中文片名": "安雅的回家路", "上映日期": "2020/03/13", "申請人": "華映娛樂股份有限公司", "出品": "13 FILMS, LLC", "上映院數": 1, "銷售票數": 37, "週票數變動率": "0.00%", "銷售金額": 2840, "累計銷售票數": 1547, "累計銷售金額": 320701}, {"序號": 72, "國別地區": "美國", "中文片名": "血衛", "上映日期": "2020/03/12", "申請人": "薩摩亞商雄讚股份有限公司台灣分公司", "出品": "Bona Film Investment Company (Pacific RIM, USA)", "上映院數": 17, "銷售票數": 129, "週票數變動率": "-54.90%", "銷售金額": 29010, "累計銷售票數": 260037, "累計銷售金額": 62022166}, {"序號": 73, "國別地區": "越南", "中文片名": "我，最親愛的", "上映日期": "2020/03/12", "申請人": "水元素文化傳媒有限公司", "出品": "SKYLINE MEDIA CO., LTD", "上映院數": 4, "銷售票數": 65, "週票數變動率": "0.00%", "銷售金額": 16315, "累計銷售票數": 2260, "累計銷售金額": 518686}, {"序號": 74, "國別地區": "英國", "中文片名": "天鵝湖", "上映日期": "2020/03/07", "申請人": "威秀影城股份有限公司", "出品": "More2Screen Limited", "上映院數": 3, "銷售票數": 7, "週票數變動率": "0.00%", "銷售金額": 5120, "累計銷售票數": 94, "累計銷售金額": 67320}, {"序號": 75, "國別地區": "南韓", "中文片名": "明明會說話", "上映日期": "2020/03/06", "申請人": "英屬蓋曼群島商威望國際娛樂股份有限公司台灣分公司", "出品": "LittleBig Pictures", "上映院數": 2, "銷售票數": 187, "週票數變動率": "679.17%", "銷售金額": 15260, "累計銷售票數": 20563, "累計銷售金額": 4514596}, {"序號": 76, "國別地區": "美國", "中文片名": "艾瑪﹒", "上映日期": "2020/03/06", "申請人": "美商美國環球影片股份有限公司台灣分公司", "出品": "UNIVERSAL INTERNATIONAL FILMS LLC", "上映院數": 3, "銷售票數": 144, "週票數變動率": "-12.20%", "銷售金額": 8875, "累計銷售票數": 4621, "累計銷售金額": 1012927}, {"序號": 77, "國別地區": "南韓", "中文片名": "大畫特務", "上映日期": "2020/03/06", "申請人": "香港商甲上娛樂有限公司台灣分公司", "出品": "LOTTE CULTUREWORKS CO., LTD.", "上映院數": 1, "銷售票數": 17, "週票數變動率": "240.00%", "銷售金額": 2720, "累計銷售票數": 51713, "累計銷售金額": 11826570}, {"序號": 78, "國別地區": "美國", "中文片名": "極地守護犬", "上映日期": "2020/03/06", "申請人": "博偉電影股份有限公司", "出品": "BUENA VISTA INTERNATIONAL, INC.", "上映院數": 6, "銷售票數": 790, "週票數變動率": "77.53%", "銷售金額": 53485, "累計銷售票數": 72655, "累計銷售金額": 16088862}, {"序號": 79, "國別地區": "中華民國", "中文片名": "狂飆一夢", "上映日期": "2020/03/06", "申請人": "廖建華影像工作室", "出品": "廖建華影像工作室##一顆星工作室有限公司", "上映院數": 1, "銷售票數": 0, "週票數變動率": "-100.00%", "銷售金額": 0, "累計銷售票數": 1626, "累計銷售金額": 354754}, {"序號": 80, "國別地區": "美國", "中文片名": "隱形人", "上映日期": "2020/02/27", "申請人": "美商美國環球影片股份有限公司台灣分公司", "出品": "UNIVERSAL INTERNATIONAL FILMS LLC", "上映院數": 6, "銷售票數": 637, "週票數變動率": "220.10%", "銷售金額": 46885, "累計銷售票數": 220952, "累計銷售金額": 52421087}, {"序號": 81, "國別地區": "中華民國", "中文片名": "女鬼橋", "上映日期": "2020/02/27", "申請人": "星泰國際娛樂股份有限公司", "出品": "樂到家國際娛樂股份有限公司##天馬傳播事業有限公司##得藝文創國際股份有限公司##大慕影藝國際事業股份有限公司##氧氣電影有限公司##華映娛樂股份有限公司##海樂影業股份有限公司", "上映院數": 3, "銷售票數": 64, "週票數變動率": "-21.95%", "銷售金額": 12760, "累計銷售票數": 251293, "累計銷售金額": 57963635}, {"序號": 82, "國別地區": "日本", "中文片名": "鳴鳥不飛：烏雲密布", "上映日期": "2020/02/27", "申請人": "采昌國際多媒體股份有限公司", "出品": "SPO Entertainment Inc.", "上映院數": 1, "銷售票數": 3, "週票數變動率": "-25.00%", "銷售金額": 750, "累計銷售票數": 28447, "累計銷售金額": 6923617}, {"序號": 83, "國別地區": "美國", "中文片名": "怨咒", "上映日期": "2020/02/27", "申請人": "美商台灣索尼影業發行股份有限公司台灣分公司", "出品": "SONY PICTURES RELEASING INTERNATIONAL CORPORATION.", "上映院數": 1, "銷售票數": 7, "週票數變動率": "-87.50%", "銷售金額": 350, "累計銷售票數": 21146, "累計銷售金額": 4709627}, {"序號": 84, "國別地區": "美國", "中文片名": "李察朱威爾事件", "上映日期": "2020/02/27", "申請人": "美商華納兄弟（遠東）股份有限公司台灣分公司", "出品": "WARNER BROS. PICTURES INTERNATIONAL.", "上映院數": 7, "銷售票數": 284, "週票數變動率": "-21.76%", "銷售金額": 21985, "累計銷售票數": 28311, "累計銷售金額": 6298246}, {"序號": 85, "國別地區": "美國", "中文片名": "音速小子", "上映日期": "2020/02/21", "申請人": "美商美國派拉蒙影片股份有限公司台灣分公司", "出品": "PARAMOUNT PICTURES CORPORATION", "上映院數": 3, "銷售票數": 270, "週票數變動率": "-21.74%", "銷售金額": 16350, "累計銷售票數": 103270, "累計銷售金額": 24078835}, {"序號": 86, "國別地區": "美國", "中文片名": "逃出夢幻島", "上映日期": "2020/02/21", "申請人": "美商台灣索尼影業發行股份有限公司台灣分公司", "出品": "SONY PICTURES RELEASING INTERNATIONAL CORPORATION.", "上映院數": 4, "銷售票數": 192, "週票數變動率": "-36.63%", "銷售金額": 17385, "累計銷售票數": 99196, "累計銷售金額": 21971797}, {"序號": 87, "國別地區": "英國", "中文片名": "羅密歐與茱麗葉", "上映日期": "2020/02/14", "申請人": "威秀影城股份有限公司", "出品": "More2Screen Limited", "上映院數": 1, "銷售票數": 11, "週票數變動率": "0.00%", "銷售金額": 7040, "累計銷售票數": 81, "累計銷售金額": 56000}, {"序號": 88, "國別地區": "美國", "中文片名": "雨天 . 紐約", "上映日期": "2020/02/14", "申請人": "香港商甲上娛樂有限公司台灣分公司", "出品": "Krisolta Film & TV (UK) LIMITED", "上映院數": 1, "銷售票數": 34, "週票數變動率": "21.43%", "銷售金額": 4880, "累計銷售票數": 11227, "累計銷售金額": 2582768}, {"序號": 89, "國別地區": "日本", "中文片名": "全境失控", "上映日期": "2020/02/14", "申請人": "采昌國際多媒體股份有限公司", "出品": "日本テレビ放送網株式会社", "上映院數": 1, "銷售票數": 13, "週票數變動率": "116.67%", "銷售金額": 1430, "累計銷售票數": 4713, "累計銷售金額": 999572}, {"序號": 90, "國別地區": "美國", "中文片名": "猛禽小隊: 小丑女大解放", "上映日期": "2020/02/14", "申請人": "美商華納兄弟（遠東）股份有限公司台灣分公司", "出品": "WARNER BROS. PICTURES INTERNATIONAL.", "上映院數": 5, "銷售票數": 451, "週票數變動率": "-19.61%", "銷售金額": 29965, "累計銷售票數": 470872, "累計銷售金額": 112402517}, {"序號": 91, "國別地區": "美國", "中文片名": 1917, "上映日期": "2020/02/06", "申請人": "美商美國環球影片股份有限公司台灣分公司", "出品": "UNIVERSAL INTERNATIONAL FILMS LLC", "上映院數": 6, "銷售票數": 642, "週票數變動率": "124.48%", "銷售金額": 41655, "累計銷售票數": 302064, "累計銷售金額": 74359898}, {"序號": 92, "國別地區": "美國", "中文片名": "杜立德", "上映日期": "2020/01/30", "申請人": "美商美國環球影片股份有限公司台灣分公司", "出品": "UNIVERSAL INTERNATIONAL FILMS LLC", "上映院數": 2, "銷售票數": 56, "週票數變動率": "-70.68%", "銷售金額": 2960, "累計銷售票數": 317961, "累計銷售金額": 75945737}, {"序號": 93, "國別地區": "中華民國", "中文片名": "你的情歌", "上映日期": "2020/01/23", "申請人": "香港商甲上娛樂有限公司台灣分公司", "出品": "奇想事企業有限公司##能率影業股份有限公司##香港商甲上娛樂有限公司台灣分公司 ##采昌國際多媒體股份有限公司  ##英屬維京群島商敦宜股份有限公司台灣分公司", "上映院數": 2, "銷售票數": 16, "週票數變動率": "-80.72%", "銷售金額": 2320, "累計銷售票數": 83214, "累計銷售金額": 19435858}, {"序號": 94, "國別地區": "美國", "中文片名": "她們", "上映日期": "2020/01/23", "申請人": "美商台灣索尼影業發行股份有限公司台灣分公司", "出品": "SONY PICTURES RELEASING INTERNATIONAL CORPORATION.", "上映院數": 5, "銷售票數": 132, "週票數變動率": "-49.43%", "銷售金額": 9785, "累計銷售票數": 92521, "累計銷售金額": 21835103}, {"序號": 95, "國別地區": "日本", "中文片名": "巧虎電影 英雄遊樂園", "上映日期": "2020/01/22", "申請人": "全民大劇團股份有限公司", "出品": "法人倍樂生株式會社", "上映院數": 17, "銷售票數": 110, "週票數變動率": "111.54%", "銷售金額": 27301, "累計銷售票數": 18189, "累計銷售金額": 4296867}, {"序號": 96, "國別地區": "美國", "中文片名": "不完美的正義", "上映日期": "2020/01/17", "申請人": "美商華納兄弟（遠東）股份有限公司台灣分公司", "出品": "WARNER BROS. PICTURES INTERNATIONAL.", "上映院數": 3, "銷售票數": 94, "週票數變動率": "80.77%", "銷售金額": 9250, "累計銷售票數": 48251, "累計銷售金額": 10945512}, {"序號": 97, "國別地區": "丹麥", "中文片名": "在黑暗中漫舞：20週年數位修復版", "上映日期": "2020/01/17", "申請人": "光年映畫有限公司", "出品": "TRUSTNORDISK APS", "上映院數": 2, "銷售票數": 28, "週票數變動率": "0.00%", "銷售金額": 5930, "累計銷售票數": 4746, "累計銷售金額": 1054376}, {"序號": 98, "國別地區": "美國", "中文片名": "絕地戰警FOR LIFE", "上映日期": "2020/01/17", "申請人": "美商台灣索尼影業發行股份有限公司台灣分公司", "出品": "SONY PICTURES RELEASING INTERNATIONAL CORPORATION.", "上映院數": 2, "銷售票數": 67, "週票數變動率": "-47.66%", "銷售金額": 3530, "累計銷售票數": 574355, "累計銷售金額": 136847465}, {"序號": 99, "國別地區": "美國", "中文片名": "兔嘲男孩", "上映日期": "2020/01/16", "申請人": "博偉電影股份有限公司", "出品": "BUENA VISTA INTERNATIONAL, INC.", "上映院數": 3, "銷售票數": 35, "週票數變動率": "-43.55%", "銷售金額": 4600, "累計銷售票數": 91101, "累計銷售金額": 21093938}, {"序號": 100, "國別地區": "香港", "中文片名": "葉問4：完結篇", "上映日期": "2020/01/03", "申請人": "華映娛樂股份有限公司", "出品": "東方影業出品有限公司", "上映院數": 4, "銷售票數": 46, "週票數變動率": "0.00%", "銷售金額": 10170, "累計銷售票數": 809261, "累計銷售金額": 185385338}, {"序號": 101, "國別地區": "美國", "中文片名": "冰雪奇緣2", "上映日期": "2019/11/21", "申請人": "台灣華特迪士尼股份有限公司", "出品": "BUENA VISTA INTERNATIONAL, INC.", "上映院數": 1, "銷售票數": 5, "週票數變動率": "-58.33%", "銷售金額": 700, "累計銷售票數": 1453817, "累計銷售金額": 343888908}, {"序號": 102, "國別地區": "日本", "中文片名": "HELLO WORLD", "上映日期": "2019/11/15", "申請人": "車庫娛樂股份有限公司", "出品": "TOHO CO., LTD.", "上映院數": 20, "銷售票數": 561, "週票數變動率": "-31.92%", "銷售金額": 142762, "累計銷售票數": 37424, "累計銷售金額": 8848993}, {"序號": 103, "國別地區": "日本", "中文片名": "為美好的世界獻上祝福！紅傳說", "上映日期": "2019/11/15", "申請人": "向洋影業有限公司", "出品": "株式会社KADOKAWA", "上映院數": 1, "銷售票數": 3, "週票數變動率": "-50.00%", "銷售金額": 810, "累計銷售票數": 42218, "累計銷售金額": 10609566}, {"序號": 104, "國別地區": "日本", "中文片名": "那一夜", "上映日期": "2019/11/13", "申請人": "天馬行空數位有限公司", "出品": "NIKKATSU CORPORATION", "上映院數": 1, "銷售票數": 19, "週票數變動率": "-63.46%", "銷售金額": 5070, "累計銷售票數": 3525, "累計銷售金額": 798069}, {"序號": 105, "國別地區": "美國", "中文片名": "星際救援", "上映日期": "2019/09/20", "申請人": "台北双喜電影發行股份有限公司", "出品": "BONA FILM INVESTMENT COMPANY", "上映院數": 8, "銷售票數": 201, "週票數變動率": "84.40%", "銷售金額": 62073, "累計銷售票數": 146324, "累計銷售金額": 34206736}, {"序號": 106, "國別地區": "日本", "中文片名": "天氣之子", "上映日期": "2019/09/12", "申請人": "車庫娛樂股份有限公司", "出品": "TOHO CO., LTD.", "上映院數": 39, "銷售票數": 3551, "週票數變動率": "0.00%", "銷售金額": 967572, "累計銷售票數": 697046, "累計銷售金額": 166570602}, {"序號": 107, "國別地區": "香港", "中文片名": "花椒之味", "上映日期": "2019/09/12", "申請人": "華映娛樂股份有限公司", "出品": "寰亞電影製作有限公司##北京拉近影業有限公司##大地時代文化傳播(北京)有限公司##英皇影業有限公司##高寶集團影視有限公司##高益創新投資公共有限公司##寰亞電影發行（北京）有限公司##中影寰亞音像製品有限公司##悅視（北京）文化傳媒有限公司##大地時代文化傳播（天津）有限公司##上海懿合文化傳媒股份有限公司##金門製作有限公司", "上映院數": 4, "銷售票數": 24, "週票數變動率": "0.00%", "銷售金額": 5670, "累計銷售票數": 27012, "累計銷售金額": 5851970}, {"序號": 108, "國別地區": "香港", "中文片名": "掃毒2 天地對決", "上映日期": "2019/07/05", "申請人": "華映娛樂股份有限公司", "出品": "寰宇娛樂有限公司##廣東昇格傳媒股份有限公司##銀都機構有限公司##映藝娛樂有限公司##太陽娛樂文化有限公司##北京合瑞影業文化有限公司", "上映院數": 4, "銷售票數": 20, "週票數變動率": "0.00%", "銷售金額": 4400, "累計銷售票數": 181054, "累計銷售金額": 40775348}, {"序號": 109, "國別地區": "加拿大", "中文片名": "哈柏太空之旅 3D", "上映日期": "2019/02/04", "申請人": "國際電影事業有限公司", "出品": "IMAX Corporation", "上映院數": 1, "銷售票數": 0, "週票數變動率": "0.00%", "銷售金額": 0, "累計銷售票數": 610, "累計銷售金額": 87400}, {"序號": 110, "國別地區": "加拿大", "中文片名": "深海獵奇 3D", "上映日期": "2019/02/03", "申請人": "國際電影事業有限公司", "出品": "IMAX Corporation", "上映院數": 1, "銷售票數": 0, "週票數變動率": "-100.00%", "銷售金額": 0, "累計銷售票數": 1205, "累計銷售金額": 149829}, {"序號": 111, "國別地區": "美國", "中文片名": "幸福綠皮書", "上映日期": "2019/01/25", "申請人": "英屬蓋曼群島商威望國際娛樂股份有限公司台灣分公司", "出品": "Storyteller Distribution Co., LLC pursuant to its arrangements with Participant Media, LLC", "上映院數": 2, "銷售票數": 14, "週票數變動率": "-53.33%", "銷售金額": 2785, "累計銷售票數": 190315, "累計銷售金額": 43502577}, {"序號": 112, "國別地區": "香港", "中文片名": "霸王別姬", "上映日期": "2018/12/14", "申請人": "能率影業股份有限公司", "出品": "湯臣(香港)電影有限公司", "上映院數": 2, "銷售票數": 1, "週票數變動率": "-66.67%", "銷售金額": 200, "累計銷售票數": 52586, "累計銷售金額": 12522767}, {"序號": 113, "國別地區": "日本", "中文片名": "夏目友人帳劇場版 緣結空蟬", "上映日期": "2018/12/07", "申請人": "木棉花國際股份有限公司", "出品": "ANIPLEX INC.", "上映院數": 10, "銷售票數": 164, "週票數變動率": "0.00%", "銷售金額": 42152, "累計銷售票數": 23270, "累計銷售金額": 5424107}, {"序號": 114, "國別地區": "日本", "中文片名": "道別的早晨就用約定之花點綴吧", "上映日期": "2018/04/04", "申請人": "向洋影業有限公司", "出品": "Hakuhodo DY music ＆ pictures Inc.", "上映院數": 1, "銷售票數": 1, "週票數變動率": "-66.67%", "銷售金額": 250, "累計銷售票數": 16400, "累計銷售金額": 4029998}, {"序號": 115, "國別地區": "美國", "中文片名": "噤界", "上映日期": "2018/01/19", "申請人": "美商美國派拉蒙影片股份有限公司台灣分公司", "出品": "PARAMOUNT PICTURES CORPORATION", "上映院數": 1, "銷售票數": 34, "週票數變動率": "30.77%", "銷售金額": 6460, "累計銷售票數": 315797, "累計銷售金額": 72426094}, {"序號": 116, "國別地區": "日本", "中文片名": "她不知道那些鳥的名字", "上映日期": "2017/12/22", "申請人": "天馬行空數位有限公司", "出品": "NIKKATSU CORPORATION", "上映院數": 1, "銷售票數": 1, "週票數變動率": "0.00%", "銷售金額": 210, "累計銷售票數": 3650, "累計銷售金額": 826620}, {"序號": 117, "國別地區": "日本", "中文片名": "魔法科高中的劣等生 呼喚繁星的少女", "上映日期": "2017/12/08", "申請人": "向洋影業有限公司", "出品": "(日本) 株式会社アニプレックス", "上映院數": 1, "銷售票數": 2, "週票數變動率": "-50.00%", "銷售金額": 480, "累計銷售票數": 20211, "累計銷售金額": 4961597}, {"序號": 118, "國別地區": "日本", "中文片名": "遊戲人生", "上映日期": "2017/11/17", "申請人": "香港商甲上娛樂有限公司台灣分公司", "出品": "(日本)KADOKAWA CORPORATION", "上映院數": 12, "銷售票數": 1161, "週票數變動率": "63.29%", "銷售金額": 423528, "累計銷售票數": 127127, "累計銷售金額": 38146656}, {"序號": 119, "國別地區": "中國大陸", "中文片名": "相愛相親", "上映日期": "2017/11/10", "申請人": "松澤國際影業股份有限公司", "出品": "(大陸)北京海潤影業有限公司##(中華民國)松澤國際影業股份有限公司", "上映院數": 1, "銷售票數": 1, "週票數變動率": "100.00%", "銷售金額": 150, "累計銷售票數": 23180, "累計銷售金額": 5153166}, {"序號": 120, "國別地區": "美國", "中文片名": "大河戀：4K數位修復版", "上映日期": "2017/08/28", "申請人": "可樂藝術文創股份有限公司", "出品": "(法國)PATHE FILMS S.A.S.", "上映院數": 2, "銷售票數": 13, "週票數變動率": "0.00%", "銷售金額": 2660, "累計銷售票數": 1409, "累計銷售金額": 289770}, {"序號": 121, "國別地區": "英國", "中文片名": "咫尺天涯", "上映日期": "2017/03/03", "申請人": "香港商甲上娛樂有限公司台灣分公司", "出品": "HANWAY FILMS LIMITED", "上映院數": 2, "銷售票數": 11, "週票數變動率": "57.14%", "銷售金額": 2380, "累計銷售票數": 537, "累計銷售金額": 114065}, {"序號": 122, "國別地區": "美國", "中文片名": "玩命關頭8", "上映日期": "2016/12/16", "申請人": "美商美國環球影片股份有限公司台灣分公司", "出品": "UNIVERSAL INTERNATIONAL FILMS LLC", "上映院數": 5, "銷售票數": 39, "週票數變動率": "-45.83%", "銷售金額": 8570, "累計銷售票數": 2674166, "累計銷售金額": 650834028}, {"序號": 123, "國別地區": "法國", "中文片名": "攻敵必救", "上映日期": "2016/12/09", "申請人": "海樂影業股份有限公司", "出品": "EUROPA CORP", "上映院數": 1, "銷售票數": 29, "週票數變動率": "1,350.00%", "銷售金額": 5725, "累計銷售票數": 47375, "累計銷售金額": 10313590}, {"序號": 124, "國別地區": "日本", "中文片名": "刀劍神域劇場版-序列爭戰", "上映日期": "2016/11/25", "申請人": "木棉花國際股份有限公司", "出品": "ANIPLEX INC.", "上映院數": 3, "銷售票數": 30, "週票數變動率": "-84.29%", "銷售金額": 12595, "累計銷售票數": 214282, "累計銷售金額": 55892514}, {"序號": 125, "國別地區": "日本", "中文片名": "愛情，突如其來", "上映日期": "2016/11/25", "申請人": "天馬行空數位有限公司", "出品": "CREI INC.", "上映院數": 1, "銷售票數": 4, "週票數變動率": "0.00%", "銷售金額": 950, "累計銷售票數": 3877, "累計銷售金額": 834040}, {"序號": 126, "國別地區": "美國", "中文片名": "樂來越愛你", "上映日期": "2016/10/07", "申請人": "英屬蓋曼群島商威望國際娛樂股份有限公司台灣分公司", "出品": "(英國)LIONS GATE INTERNATIONAL (UK) LIMITED", "上映院數": 2, "銷售票數": 57, "週票數變動率": "42.50%", "銷售金額": 17271, "累計銷售票數": 562543, "累計銷售金額": 133026092}, {"序號": 127, "國別地區": "法國", "中文片名": "終極追殺令", "上映日期": "2016/09/02", "申請人": "南強國際影視傳播有限公司", "出品": "GAUMONT", "上映院數": 2, "銷售票數": 367, "週票數變動率": "149.66%", "銷售金額": 82535, "累計銷售票數": 7354, "累計銷售金額": 1692629}, {"序號": 128, "國別地區": "美國", "中文片名": "鋼鐵英雄", "上映日期": "2016/09/02", "申請人": "香港商甲上娛樂有限公司台灣分公司", "出品": "IM GLOBAL, LLC", "上映院數": 3, "銷售票數": 6, "週票數變動率": "100.00%", "銷售金額": 1340, "累計銷售票數": 507800, "累計銷售金額": 115721226}, {"序號": 129, "國別地區": "美國", "中文片名": "列車上的女孩", "上映日期": "2016/08/26", "申請人": "美商美國環球影片股份有限公司台灣分公司", "出品": "UNIVERSAL INTERNATIONAL FILMS LLC", "上映院數": 1, "銷售票數": 17, "週票數變動率": "-19.05%", "銷售金額": 2855, "累計銷售票數": 123035, "累計銷售金額": 28016212}, {"序號": 130, "國別地區": "英國", "中文片名": "巴黎，德州", "上映日期": "2016/07/22", "申請人": "香港商甲上娛樂有限公司台灣分公司", "出品": "HANWAY FILMS LIMITED", "上映院數": 1, "銷售票數": 37, "週票數變動率": "68.18%", "銷售金額": 7580, "累計銷售票數": 2035, "累計銷售金額": 448705}, {"序號": 131, "國別地區": "英國", "中文片名": "慾望之翼", "上映日期": "2011/05/13", "申請人": "香港商甲上娛樂有限公司台灣分公司", "出品": "HANWAY FILMS LIMITED", "上映院數": 1, "銷售票數": 14, "週票數變動率": "75.00%", "銷售金額": 3010, "累計銷售票數": 2077, "累計銷售金額": 441540}, {"序號": 132, "國別地區": "法國", "中文片名": "艾蜜莉的異想世界", "上映日期": "2002/03/08", "申請人": "南強國際影視傳播有限公司", "出品": "GAUMONT S.A.", "上映院數": 1, "銷售票數": 149, "週票數變動率": "0.00%", "銷售金額": 33070, "累計銷售票數": 6025, "累計銷售金額": 1318235}, {"序號": 133, "國別地區": "法國", "中文片名": "碧海藍天", "上映日期": "2002/03/08", "申請人": "南強國際影視傳播有限公司", "出品": "GAUMONT", "上映院數": 1, "銷售票數": 213, "週票數變動率": "65.12%", "銷售金額": 47905, "累計銷售票數": 8860, "累計銷售金額": 2022650}, {"序號": 134, "國別地區": "日本", "中文片名": "失樂園", "上映日期": "1998/02/07", "申請人": "可樂藝術文創股份有限公司", "出品": "KADOKAWA CORPORATION", "上映院數": 2, "銷售票數": 3, "週票數變動率": "-50.00%", "銷售金額": 600, "累計銷售票數": 1753, "累計銷售金額": 367200}, {"序號": 135, "國別地區": "法國", "中文片名": "藍色情挑 經典數位修復", "上映日期": "1998/02/07", "申請人": "天馬行空數位有限公司", "出品": "MK2 - SOCIÉTÉ PAR ACTIONS SIMPLIFIÉE", "上映院數": 1, "銷售票數": 8, "週票數變動率": "0.00%", "銷售金額": 1796, "累計銷售票數": 3328, "累計銷售金額": 688815}, {"序號": 136, "國別地區": "中國大陸", "中文片名": "親愛的", "上映日期": "1995/03/10", "申請人": "香港商甲上娛樂有限公司台灣分公司", "出品": "香港星美影業有限公司##我們製作有限公司##大陸阿里巴巴影業集團有限公司##北京光綫影業有限公司##北京嘉映影業有限公司##上海三次元影視傳媒有限公司##黃渤(上海)影視文化工作室##北京普林賽司文化傳播有限責任公司##北京快樂新升文化傳播有限公司", "上映院數": 1, "銷售票數": 1, "週票數變動率": "0.00%", "銷售金額": 230, "累計銷售票數": 2, "累計銷售金額": 520}, {"序號": 137, "國別地區": "美國", "中文片名": "刺激1995", "上映日期": "1995/03/10", "申請人": "美商華納兄弟（遠東）股份有限公司台灣分公司", "出品": "WARNER BROS. PICTURES INTERNATIONAL.", "上映院數": 6, "銷售票數": 102, "週票數變動率": "-35.44%", "銷售金額": 25971, "累計銷售票數": 23685, "累計銷售金額": 5780347}, {"序號": 138, "國別地區": "香港", "中文片名": "阿飛正傳", "上映日期": "1990/12/22", "申請人": "華映娛樂股份有限公司", "出品": "(英屬維京群島)EAST ASIA FILMS DISTRIBUTION LIMITED##(香港)ESUN.COM LIMITED", "上映院數": 1, "銷售票數": 37, "週票數變動率": "-33.93%", "銷售金額": 7820, "累計銷售票數": 7098, "累計銷售金額": 1633625}, {"序號": 139, "國別地區": "義大利", "中文片名": "海上鋼琴師", "上映日期": "1990/12/22", "申請人": "海鵬影業有限公司", "出品": "True Colours Glorious Films Srl", "上映院數": 3, "銷售票數": 75, "週票數變動率": "-5.06%", "銷售金額": 17040, "累計銷售票數": 18136, "累計銷售金額": 4134728}, {"序號": 140, "國別地區": "義大利", "中文片名": "新天堂樂園", "上映日期": "1990/05/12", "申請人": "香港商甲上娛樂有限公司台灣分公司", "出品": "CRISTAL DI FILM", "上映院數": 1, "銷售票數": 8, "週票數變動率": "14.29%", "銷售金額": 2180, "累計銷售票數": 877, "累計銷售金額": 156700}]