[{"序號": 1, "國別地區": "美國", "中文片名": "依然相信", "上映日期": "2020/03/20", "申請人": "車庫娛樂股份有限公司", "出品": "LIONS GATE INTERNATIONAL (UK) LIMITED", "上映院數": 52, "銷售票數": 2476, "週票數變動率": "-3.05%", "銷售金額": 587792, "累計銷售票數": 5030, "累計銷售金額": 1189007}, {"序號": 2, "國別地區": "美國", "中文片名": "A+瞎妹", "上映日期": "2020/03/20", "申請人": "車庫娛樂股份有限公司", "出品": "METRO-GOLDWYN-MAYER STUDIOS INC.", "上映院數": 34, "銷售票數": 1291, "週票數變動率": "5.13%", "銷售金額": 297870, "累計銷售票數": 2519, "累計銷售金額": 580804}, {"序號": 3, "國別地區": "法國", "中文片名": "我出去醫下", "上映日期": "2020/03/20", "申請人": "原創娛樂股份有限公司", "出品": "Other Angle Pictures", "上映院數": 32, "銷售票數": 1078, "週票數變動率": "-10.61%", "銷售金額": 239237, "累計銷售票數": 2284, "累計銷售金額": 513271}, {"序號": 4, "國別地區": "南韓", "中文片名": "神之一手：鬼手篇", "上映日期": "2020/03/20", "申請人": "車庫娛樂股份有限公司", "出品": "CJ ENM CO., LTD.", "上映院數": 24, "銷售票數": 984, "週票數變動率": "-10.71%", "銷售金額": 223020, "累計銷售票數": 2086, "累計銷售金額": 477376}, {"序號": 5, "國別地區": "美國", "中文片名": "最後晚安曲", "上映日期": "2020/03/20", "申請人": "本萃電影有限公司", "出品": "Westend Films Ltd.", "上映院數": 37, "銷售票數": 715, "週票數變動率": "-16.08%", "銷售金額": 155353, "累計銷售票數": 1567, "累計銷售金額": 336730}, {"序號": 6, "國別地區": "日本", "中文片名": "搖滾師匠：細野晴臣", "上映日期": "2020/03/20", "申請人": "中影股份有限公司", "出品": "日活株式會社(NIKKATSU CORPORATION)", "上映院數": 10, "銷售票數": 459, "週票數變動率": "31.90%", "銷售金額": 98620, "累計銷售票數": 807, "累計銷售金額": 172165}, {"序號": 7, "國別地區": "德國", "中文片名": "不愛鋼琴師", "上映日期": "2020/03/20", "申請人": "光年映畫有限公司", "出品": "Beta Cinema GmbH", "上映院數": 6, "銷售票數": 369, "週票數變動率": "27.24%", "銷售金額": 78610, "累計銷售票數": 659, "累計銷售金額": 141540}, {"序號": 8, "國別地區": "英國", "中文片名": "囚愛之家", "上映日期": "2020/03/20", "申請人": "暗光鳥有限公司", "出品": "CM SALES, LLC", "上映院數": 5, "銷售票數": 57, "週票數變動率": "-33.72%", "銷售金額": 12087, "累計銷售票數": 143, "累計銷售金額": 30741}, {"序號": 9, "國別地區": "日本", "中文片名": "我的失蹤爸爸", "上映日期": "2020/03/20", "申請人": "輝洪開發股份有限公司", "出品": "SDP", "上映院數": 1, "銷售票數": 33, "週票數變動率": "26.92%", "銷售金額": 6625, "累計銷售票數": 59, "累計銷售金額": 11985}, {"序號": 10, "國別地區": "中華民國", "中文片名": "練愛iNG", "上映日期": "2020/03/13", "申請人": "威視股份有限公司", "出品": "量能文創股份有限公司##聚善美文創娛樂有限公司##遊戲橘子數位科技股份有限公司##恆動工作室##天鵬翱翔集團有限公司", "上映院數": 59, "銷售票數": 7439, "週票數變動率": "-46.66%", "銷售金額": 1738987, "累計銷售票數": 33557, "累計銷售金額": 7798044}, {"序號": 11, "國別地區": "日本", "中文片名": "劇場版 不起眼女主角培育法 Fine", "上映日期": "2020/03/13", "申請人": "車庫娛樂股份有限公司", "出品": "ANIPLEX INC.", "上映院數": 20, "銷售票數": 2288, "週票數變動率": "-59.11%", "銷售金額": 561645, "累計銷售票數": 17164, "累計銷售金額": 4188386}, {"序號": 12, "國別地區": "美國", "中文片名": "鋼鐵勳章", "上映日期": "2020/03/13", "申請人": "采昌國際多媒體股份有限公司", "出品": "Freeway Entertainment Kft", "上映院數": 54, "銷售票數": 1508, "週票數變動率": "-69.86%", "銷售金額": 340630, "累計銷售票數": 11779, "累計銷售金額": 2655593}, {"序號": 13, "國別地區": "泰國", "中文片名": "通靈少年2020", "上映日期": "2020/03/13", "申請人": "英屬維京群島商高捷全球開發有限公司 台灣分公司", "出品": "Sahamongkolfilm International Co., Ltd.", "上映院數": 30, "銷售票數": 353, "週票數變動率": "-82.07%", "銷售金額": 77550, "累計銷售票數": 4470, "累計銷售金額": 965988}, {"序號": 14, "國別地區": "南韓", "中文片名": "南山的部長們", "上映日期": "2020/03/13", "申請人": "車庫娛樂股份有限公司", "出品": "SHOWBOX CORP.", "上映院數": 16, "銷售票數": 292, "週票數變動率": "-70.95%", "銷售金額": 67672, "累計銷售票數": 2199, "累計銷售金額": 518369}, {"序號": 15, "國別地區": "波蘭", "中文片名": "另類神父", "上映日期": "2020/03/13", "申請人": "聯影企業股份有限公司", "出品": "New Europe Film Sales", "上映院數": 9, "銷售票數": 265, "週票數變動率": "-67.32%", "銷售金額": 57337, "累計銷售票數": 1834, "累計銷售金額": 385752}, {"序號": 16, "國別地區": "日本", "中文片名": "電影版 地獄少女", "上映日期": "2020/03/13", "申請人": "車庫娛樂股份有限公司", "出品": "GAGA CORPORATION", "上映院數": 17, "銷售票數": 194, "週票數變動率": "-75.72%", "銷售金額": 43505, "累計銷售票數": 1967, "累計銷售金額": 443975}, {"序號": 17, "國別地區": "美國", "中文片名": "安雅的回家路", "上映日期": "2020/03/13", "申請人": "華映娛樂股份有限公司", "出品": "13 FILMS, LLC", "上映院數": 21, "銷售票數": 102, "週票數變動率": "-79.84%", "銷售金額": 21905, "累計銷售票數": 1476, "累計銷售金額": 312481}, {"序號": 18, "國別地區": "中國大陸", "中文片名": "破．局", "上映日期": "2020/03/13", "申請人": "恆星多媒體股份有限公司", "出品": "西藏恒信天地影視有限公司##霍爾果斯捷成瑞吉祥影視傳媒有限公司##北京春秋永樂文化傳播股份有限公司##天津貓眼文化傳媒有限公司##星空盛典影業(深圳)股份有限公司##深圳市東方富海投資管理股份有限公司##喀什嘉映文化傳媒有限公司##偉世兄弟文化傳媒有限公司##天津筋斗雲影視文化傳媒有限公司##上海博納文化傳媒有限公司##嘉映影業有限公司##宸銘影業(上海)有限公司##霍爾果斯宸銘影業有限公司##北京怪獸影視文化傳媒有限公司", "上映院數": 1, "銷售票數": 53, "週票數變動率": "-56.91%", "銷售金額": 11825, "累計銷售票數": 323, "累計銷售金額": 72870}, {"序號": 19, "國別地區": "美國", "中文片名": "牆內的房客", "上映日期": "2020/03/13", "申請人": "暗光鳥有限公司", "出品": "MPI MEDIA GROUP", "上映院數": 4, "銷售票數": 47, "週票數變動率": "-53.47%", "銷售金額": 10370, "累計銷售票數": 272, "累計銷售金額": 59808}, {"序號": 20, "國別地區": "英國", "中文片名": "複製柔伊", "上映日期": "2020/03/13", "申請人": "天馬行空數位有限公司", "出品": "PROTAGONIST PICTURES LIMITED", "上映院數": 3, "銷售票數": 35, "週票數變動率": "-79.89%", "銷售金額": 7300, "累計銷售票數": 376, "累計銷售金額": 77435}, {"序號": 21, "國別地區": "美國", "中文片名": "血衛", "上映日期": "2020/03/12", "申請人": "薩摩亞商雄讚股份有限公司台灣分公司", "出品": "Bona Film Investment Company (Pacific RIM, USA)", "上映院數": 99, "銷售票數": 28765, "週票數變動率": "-62.01%", "銷售金額": 6830580, "累計銷售票數": 237322, "累計銷售金額": 56648745}, {"序號": 22, "國別地區": "越南", "中文片名": "我，最親愛的", "上映日期": "2020/03/12", "申請人": "水元素文化傳媒有限公司", "出品": "SKYLINE MEDIA CO., LTD", "上映院數": 13, "銷售票數": 259, "週票數變動率": "-69.64%", "銷售金額": 58944, "累計銷售票數": 2168, "累計銷售金額": 495966}, {"序號": 23, "國別地區": "英國", "中文片名": "天鵝湖", "上映日期": "2020/03/07", "申請人": "威秀影城股份有限公司", "出品": "More2Screen Limited", "上映院數": 1, "銷售票數": 6, "週票數變動率": "-78.57%", "銷售金額": 4000, "累計銷售票數": 71, "累計銷售金額": 50600}, {"序號": 24, "國別地區": "南韓", "中文片名": "大畫特務", "上映日期": "2020/03/06", "申請人": "香港商甲上娛樂有限公司台灣分公司", "出品": "LOTTE CULTUREWORKS CO., LTD.", "上映院數": 82, "銷售票數": 2409, "週票數變動率": "-64.21%", "銷售金額": 536213, "累計銷售票數": 51012, "累計銷售金額": 11672349}, {"序號": 25, "國別地區": "南韓", "中文片名": "明明會說話", "上映日期": "2020/03/06", "申請人": "英屬蓋曼群島商威望國際娛樂股份有限公司台灣分公司", "出品": "LittleBig Pictures", "上映院數": 46, "銷售票數": 472, "週票數變動率": "-76.99%", "銷售金額": 105768, "累計銷售票數": 20190, "累計銷售金額": 4463056}, {"序號": 26, "國別地區": "法國", "中文片名": "導演先生的完美假期", "上映日期": "2020/03/06", "申請人": "繁盛映畫有限公司", "出品": "Wild Bunch", "上映院數": 4, "銷售票數": 228, "週票數變動率": "-40.00%", "銷售金額": 49355, "累計銷售票數": 2684, "累計銷售金額": 571702}, {"序號": 27, "國別地區": "美國", "中文片名": "艾瑪﹒", "上映日期": "2020/03/06", "申請人": "美商美國環球影片股份有限公司台灣分公司", "出品": "UNIVERSAL INTERNATIONAL FILMS LLC", "上映院數": 10, "銷售票數": 142, "週票數變動率": "-72.64%", "銷售金額": 31645, "累計銷售票數": 4171, "累計銷售金額": 980957}, {"序號": 28, "國別地區": "英國", "中文片名": "親愛的莎瑪", "上映日期": "2020/03/06", "申請人": "海鵬影業有限公司", "出品": "Autlook Filmsales GmbH", "上映院數": 4, "銷售票數": 60, "週票數變動率": "-74.03%", "銷售金額": 13250, "累計銷售票數": 1947, "累計銷售金額": 412572}, {"序號": 29, "國別地區": "美國", "中文片名": "戰慄糖果屋", "上映日期": "2020/03/06", "申請人": "車庫娛樂股份有限公司", "出品": "METRO-GOLDWYN-MAYER STUDIOS INC.", "上映院數": 11, "銷售票數": 51, "週票數變動率": "-91.60%", "銷售金額": 12215, "累計銷售票數": 8019, "累計銷售金額": 1863398}, {"序號": 30, "國別地區": "北馬其頓", "中文片名": "大地蜜語", "上映日期": "2020/03/06", "申請人": "車庫娛樂股份有限公司", "出品": "DECKERT DISTRIBUTION GMBH", "上映院數": 2, "銷售票數": 32, "週票數變動率": "-84.76%", "銷售金額": 7255, "累計銷售票數": 1261, "累計銷售金額": 266521}, {"序號": 31, "國別地區": "日本", "中文片名": "罪樂園", "上映日期": "2020/03/06", "申請人": "海樂影業股份有限公司", "出品": "KADOKAWA CORPORATION", "上映院數": 1, "銷售票數": 5, "週票數變動率": "-89.13%", "銷售金額": 1360, "累計銷售票數": 964, "累計銷售金額": 203501}, {"序號": 32, "國別地區": "美國", "中文片名": "隱形人", "上映日期": "2020/02/27", "申請人": "美商美國環球影片股份有限公司台灣分公司", "出品": "UNIVERSAL INTERNATIONAL FILMS LLC", "上映院數": 95, "銷售票數": 6949, "週票數變動率": "-58.39%", "銷售金額": 1623895, "累計銷售票數": 216622, "累計銷售金額": 51493069}, {"序號": 33, "國別地區": "中華民國", "中文片名": "女鬼橋", "上映日期": "2020/02/27", "申請人": "星泰國際娛樂股份有限公司", "出品": "樂到家國際娛樂股份有限公司##天馬傳播事業有限公司##得藝文創國際股份有限公司##大慕影藝國際事業股份有限公司##氧氣電影有限公司##華映娛樂股份有限公司##海樂影業股份有限公司", "上映院數": 84, "銷售票數": 6973, "週票數變動率": "-59.08%", "銷售金額": 1596181, "累計銷售票數": 246484, "累計銷售金額": 56858274}, {"序號": 34, "國別地區": "日本", "中文片名": "鳴鳥不飛：烏雲密布", "上映日期": "2020/02/27", "申請人": "采昌國際多媒體股份有限公司", "出品": "SPO Entertainment Inc.", "上映院數": 13, "銷售票數": 936, "週票數變動率": "-52.32%", "銷售金額": 230729, "累計銷售票數": 27672, "累計銷售金額": 6734802}, {"序號": 35, "國別地區": "美國", "中文片名": "極地守護犬", "上映日期": "2020/02/27", "申請人": "博偉電影股份有限公司", "出品": "BUENA VISTA INTERNATIONAL, INC.", "上映院數": 64, "銷售票數": 1001, "週票數變動率": "-63.47%", "銷售金額": 228791, "累計銷售票數": 71041, "累計銷售金額": 15934145}, {"序號": 36, "國別地區": "日本", "中文片名": "哥布林殺手：GOBLIN'S CROWN", "上映日期": "2020/02/27", "申請人": "木棉花國際股份有限公司", "出品": "Hakuhodo DY music & pictures Inc.", "上映院數": 15, "銷售票數": 173, "週票數變動率": "-63.88%", "銷售金額": 41767, "累計銷售票數": 23313, "累計銷售金額": 5544216}, {"序號": 37, "國別地區": "美國", "中文片名": "怨咒", "上映日期": "2020/02/27", "申請人": "美商台灣索尼影業發行股份有限公司台灣分公司", "出品": "SONY PICTURES RELEASING INTERNATIONAL CORPORATION.", "上映院數": 17, "銷售票數": 117, "週票數變動率": "-78.49%", "銷售金額": 26730, "累計銷售票數": 20822, "累計銷售金額": 4687372}, {"序號": 38, "國別地區": "瑞典", "中文片名": "千日千夜", "上映日期": "2020/02/27", "申請人": "東昊影業有限公司", "出品": "Roy Andersson Filmproduktion AB", "上映院數": 1, "銷售票數": 59, "週票數變動率": "-69.90%", "銷售金額": 13680, "累計銷售票數": 2540, "累計銷售金額": 553412}, {"序號": 39, "國別地區": "香港", "中文片名": "叔．叔", "上映日期": "2020/02/27", "申請人": "采昌國際多媒體股份有限公司", "出品": "先響電影有限公司New Voice Film Productions Ltd", "上映院數": 1, "銷售票數": 4, "週票數變動率": "-95.06%", "銷售金額": 1100, "累計銷售票數": 2705, "累計銷售金額": 610306}, {"序號": 40, "國別地區": "泰國", "中文片名": "娘娘腔日記", "上映日期": "2020/02/27", "申請人": "車庫娛樂股份有限公司", "出品": "GDH 559 COMPANY LIMITED", "上映院數": 2, "銷售票數": 5, "週票數變動率": "-87.80%", "銷售金額": 1090, "累計銷售票數": 7491, "累計銷售金額": 1727346}, {"序號": 41, "國別地區": "美國", "中文片名": "音速小子", "上映日期": "2020/02/21", "申請人": "美商美國派拉蒙影片股份有限公司台灣分公司", "出品": "PARAMOUNT PICTURES CORPORATION", "上映院數": 37, "銷售票數": 274, "週票數變動率": "-74.03%", "銷售金額": 64247, "累計銷售票數": 102331, "累計銷售金額": 24006384}, {"序號": 42, "國別地區": "美國", "中文片名": "李察朱威爾事件", "上映日期": "2020/02/21", "申請人": "美商華納兄弟（遠東）股份有限公司台灣分公司", "出品": "WARNER BROS. PICTURES INTERNATIONAL.", "上映院數": 5, "銷售票數": 60, "週票數變動率": "-64.91%", "銷售金額": 13665, "累計銷售票數": 27294, "累計銷售金額": 6222696}, {"序號": 43, "國別地區": "西班牙", "中文片名": "絕命大平台", "上映日期": "2020/02/21", "申請人": "原創娛樂股份有限公司", "出品": "Latido Consorcio De Exportacion Del Cine Espanol SL", "上映院數": 3, "銷售票數": 39, "週票數變動率": "-46.58%", "銷售金額": 9020, "累計銷售票數": 7251, "累計銷售金額": 1602603}, {"序號": 44, "國別地區": "美國", "中文片名": "電影音效傳奇：好萊塢之聲", "上映日期": "2020/02/21", "申請人": "造次文化有限公司", "出品": "Dogwoof Ltd", "上映院數": 2, "銷售票數": 25, "週票數變動率": "-81.75%", "銷售金額": 6260, "累計銷售票數": 4251, "累計銷售金額": 989896}, {"序號": 45, "國別地區": "南韓", "中文片名": "陰櫥", "上映日期": "2020/02/21", "申請人": "車庫娛樂股份有限公司", "出品": "CJ ENM CO., LTD.", "上映院數": 2, "銷售票數": 12, "週票數變動率": "-85.19%", "銷售金額": 2435, "累計銷售票數": 30277, "累計銷售金額": 7112535}, {"序號": 46, "國別地區": "法國", "中文片名": "悲慘世界", "上映日期": "2020/02/21", "申請人": "海鵬影業有限公司", "出品": "WILD BUNCH", "上映院數": 2, "銷售票數": 2, "週票數變動率": "-93.10%", "銷售金額": 410, "累計銷售票數": 3213, "累計銷售金額": 687448}, {"序號": 47, "國別地區": "法國", "中文片名": "閃閃小超人電影版", "上映日期": "2020/02/21", "申請人": "采昌國際多媒體股份有限公司", "出品": "STUDIOCANAL", "上映院數": 1, "銷售票數": 0, "週票數變動率": "-100.00%", "銷售金額": 0, "累計銷售票數": 1158, "累計銷售金額": 257622}, {"序號": 48, "國別地區": "南韓", "中文片名": "超\"人\"氣動物園", "上映日期": "2020/02/14", "申請人": "車庫娛樂股份有限公司", "出品": "FINECUT CO., LTD.", "上映院數": 12, "銷售票數": 61, "週票數變動率": "-83.86%", "銷售金額": 14323, "累計銷售票數": 139400, "累計銷售金額": 32520396}, {"序號": 49, "國別地區": "日本", "中文片名": "全境失控", "上映日期": "2020/02/14", "申請人": "采昌國際多媒體股份有限公司", "出品": "日本テレビ放送網株式会社", "上映院數": 2, "銷售票數": 90, "週票數變動率": "23.29%", "銷售金額": 8440, "累計銷售票數": 4602, "累計銷售金額": 986122}, {"序號": 50, "國別地區": "美國", "中文片名": "雨天 . 紐約", "上映日期": "2020/02/14", "申請人": "香港商甲上娛樂有限公司台灣分公司", "出品": "Krisolta Film & TV (UK) LIMITED", "上映院數": 1, "銷售票數": 22, "週票數變動率": "-68.12%", "銷售金額": 4920, "累計銷售票數": 11096, "累計銷售金額": 2562818}, {"序號": 51, "國別地區": "美國", "中文片名": "逃出夢幻島", "上映日期": "2020/02/14", "申請人": "美商台灣索尼影業發行股份有限公司台灣分公司", "出品": "SONY PICTURES RELEASING INTERNATIONAL CORPORATION.", "上映院數": 2, "銷售票數": 6, "週票數變動率": "-89.66%", "銷售金額": 1535, "累計銷售票數": 97879, "累計銷售金額": 21881072}, {"序號": 52, "國別地區": "美國", "中文片名": "我的寶貝男孩", "上映日期": "2020/02/07", "申請人": "美商台灣索尼影業發行股份有限公司台灣分公司", "出品": "SONY PICTURES RELEASING INTERNATIONAL CORPORATION.", "上映院數": 4, "銷售票數": 201, "週票數變動率": "55.81%", "銷售金額": 16350, "累計銷售票數": 1361, "累計銷售金額": 250529}, {"序號": 53, "國別地區": "美國", "中文片名": "猛禽小隊: 小丑女大解放", "上映日期": "2020/02/06", "申請人": "美商華納兄弟（遠東）股份有限公司台灣分公司", "出品": "WARNER BROS. PICTURES INTERNATIONAL.", "上映院數": 6, "銷售票數": 74, "週票數變動率": "-75.82%", "銷售金額": 17862, "累計銷售票數": 469531, "累計銷售金額": 112308587}, {"序號": 54, "國別地區": "日本", "中文片名": "王牌辯士", "上映日期": "2020/01/31", "申請人": "天馬行空數位有限公司", "出品": "TOEI COMPANY, LTD.", "上映院數": 2, "銷售票數": 56, "週票數變動率": "47.37%", "銷售金額": 8480, "累計銷售票數": 1397, "累計銷售金額": 294095}, {"序號": 55, "國別地區": "美國", "中文片名": 1917, "上映日期": "2020/01/30", "申請人": "美商美國環球影片股份有限公司台灣分公司", "出品": "UNIVERSAL INTERNATIONAL FILMS LLC", "上映院數": 15, "銷售票數": 1234, "週票數變動率": "78.58%", "銷售金額": 394692, "累計銷售票數": 297145, "累計銷售金額": 73155452}, {"序號": 56, "國別地區": "南韓", "中文片名": "紅鞋公主與七矮人", "上映日期": "2020/01/30", "申請人": "可樂藝術文創股份有限公司", "出品": "FINECUT CO., LTD", "上映院數": 3, "銷售票數": 3, "週票數變動率": "-76.92%", "銷售金額": 770, "累計銷售票數": 22634, "累計銷售金額": 5229627}, {"序號": 57, "國別地區": "香港", "中文片名": "肥龍過江", "上映日期": "2020/01/23", "申請人": "華映娛樂股份有限公司", "出品": "星王朝有限公司##上海博納文化傳媒有限公司##博納影業集團股份有限公司##上海新文化影業有限公司##電視廣播有限公司##太陽娛樂文化有限公司##上海杠杠影視文化有限公司##霍爾果斯環星影視傳媒有限公司##上海優創影視文化有限公司", "上映院數": 3, "銷售票數": 291, "週票數變動率": "0.00%", "銷售金額": 18570, "累計銷售票數": 61349, "累計銷售金額": 13550302}, {"序號": 58, "國別地區": "美國", "中文片名": "她們", "上映日期": "2020/01/22", "申請人": "美商台灣索尼影業發行股份有限公司台灣分公司", "出品": "SONY PICTURES RELEASING INTERNATIONAL CORPORATION.", "上映院數": 4, "銷售票數": 58, "週票數變動率": "-73.02%", "銷售金額": 13725, "累計銷售票數": 91305, "累計銷售金額": 21742203}, {"序號": 59, "國別地區": "日本", "中文片名": "巧虎電影 英雄遊樂園", "上映日期": "2020/01/17", "申請人": "全民大劇團股份有限公司", "出品": "法人倍樂生株式會社", "上映院數": 17, "銷售票數": 48, "週票數變動率": "33.33%", "銷售金額": 11270, "累計銷售票數": 17799, "累計銷售金額": 4201386}, {"序號": 60, "國別地區": "南韓", "中文片名": "青春催落去", "上映日期": "2020/01/17", "申請人": "車庫娛樂股份有限公司", "出品": "CONTENTS PANDA", "上映院數": 2, "銷售票數": 60, "週票數變動率": "-34.07%", "銷售金額": 7400, "累計銷售票數": 5459, "累計銷售金額": 1172740}, {"序號": 61, "國別地區": "美國", "中文片名": "不完美的正義", "上映日期": "2020/01/17", "申請人": "美商華納兄弟（遠東）股份有限公司台灣分公司", "出品": "WARNER BROS. PICTURES INTERNATIONAL.", "上映院數": 1, "銷售票數": 30, "週票數變動率": "0.00%", "銷售金額": 4800, "累計銷售票數": 47003, "累計銷售金額": 10849997}, {"序號": 62, "國別地區": "美國", "中文片名": "絕地戰警FOR LIFE", "上映日期": "2020/01/16", "申請人": "美商台灣索尼影業發行股份有限公司台灣分公司", "出品": "SONY PICTURES RELEASING INTERNATIONAL CORPORATION.", "上映院數": 1, "銷售票數": 9, "週票數變動率": "0.00%", "銷售金額": 2430, "累計銷售票數": 571680, "累計銷售金額": 136648700}, {"序號": 63, "國別地區": "西班牙", "中文片名": "逃出天堂島", "上映日期": "2020/01/10", "申請人": "海樂影業股份有限公司", "出品": "GEM ENTERTAINMENT KFT.", "上映院數": 3, "銷售票數": 193, "週票數變動率": "-39.88%", "銷售金額": 11930, "累計銷售票數": 7494, "累計銷售金額": 1467312}, {"序號": 64, "國別地區": "法國", "中文片名": "星星知我心", "上映日期": "2020/01/10", "申請人": "采昌國際多媒體股份有限公司", "出品": "PATHE FILMS S.A.S", "上映院數": 2, "銷售票數": 54, "週票數變動率": "-1.82%", "銷售金額": 2960, "累計銷售票數": 1551, "累計銷售金額": 300105}, {"序號": 65, "國別地區": "印度", "中文片名": "真愛裁會贏", "上映日期": "2020/01/03", "申請人": "水元素文化傳媒有限公司", "出品": "YASH RAJ FILMS PRIVATE LIMITED", "上映院數": 4, "銷售票數": 288, "週票數變動率": "-2.70%", "銷售金額": 18960, "累計銷售票數": 6838, "累計銷售金額": 1325906}, {"序號": 66, "國別地區": "美國", "中文片名": "別告訴她", "上映日期": "2020/01/03", "申請人": "車庫娛樂股份有限公司", "出品": "A24 INTERNATIONAL, LLC", "上映院數": 2, "銷售票數": 96, "週票數變動率": "21.52%", "銷售金額": 8200, "累計銷售票數": 10795, "累計銷售金額": 2345888}, {"序號": 67, "國別地區": "俄羅斯", "中文片名": "陰兒", "上映日期": "2020/01/03", "申請人": "可樂藝術文創股份有限公司", "出品": "REASON8 Films Ltd.", "上映院數": 1, "銷售票數": 18, "週票數變動率": "-40.00%", "銷售金額": 2680, "累計銷售票數": 2104, "累計銷售金額": 466310}, {"序號": 68, "國別地區": "美國", "中文片名": "霹靂嬌娃", "上映日期": "2019/12/27", "申請人": "美商台灣索尼影業發行股份有限公司台灣分公司", "出品": "SONY PICTURES RELEASING INTERNATIONAL CORPORATION.", "上映院數": 1, "銷售票數": 26, "週票數變動率": "-65.79%", "銷售金額": 3840, "累計銷售票數": 129168, "累計銷售金額": 28916759}, {"序號": 69, "國別地區": "美國", "中文片名": "CATS 貓", "上映日期": "2019/12/24", "申請人": "美商美國環球影片股份有限公司台灣分公司", "出品": "UNIVERSAL INTERNATIONAL FILMS LLC", "上映院數": 3, "銷售票數": 99, "週票數變動率": "-29.79%", "銷售金額": 9165, "累計銷售票數": 51176, "累計銷售金額": 11802801}, {"序號": 70, "國別地區": "法國", "中文片名": "燃燒女子的畫像", "上映日期": "2019/12/20", "申請人": "東昊影業有限公司", "出品": "MK2 Films", "上映院數": 1, "銷售票數": 40, "週票數變動率": "100.00%", "銷售金額": 6180, "累計銷售票數": 15118, "累計銷售金額": 3335528}, {"序號": 71, "國別地區": "香港", "中文片名": "葉問4：完結篇", "上映日期": "2019/12/19", "申請人": "華映娛樂股份有限公司", "出品": "東方影業出品有限公司", "上映院數": 8, "銷售票數": 922, "週票數變動率": "0.00%", "銷售金額": 75120, "累計銷售票數": 807470, "累計銷售金額": 185225678}, {"序號": 72, "國別地區": "美國", "中文片名": "STAR WARS : 天行者的崛起", "上映日期": "2019/12/18", "申請人": "台灣華特迪士尼股份有限公司", "出品": "BUENA VISTA INTERNATIONAL, INC.", "上映院數": 7, "銷售票數": 217, "週票數變動率": "-61.46%", "銷售金額": 21970, "累計銷售票數": 328148, "累計銷售金額": 82495684}, {"序號": 73, "國別地區": "加拿大", "中文片名": "8級警戒", "上映日期": "2019/12/13", "申請人": "車庫娛樂股份有限公司", "出品": "XYZ FILMS, LLC", "上映院數": 2, "銷售票數": 117, "週票數變動率": "37.65%", "銷售金額": 9980, "累計銷售票數": 5620, "累計銷售金額": 1136363}, {"序號": 74, "國別地區": "英國", "中文片名": "給我一個參選的理由", "上映日期": "2019/12/11", "申請人": "威秀影城股份有限公司", "出品": "The Royal National Theatre", "上映院數": 1, "銷售票數": 1, "週票數變動率": "0.00%", "銷售金額": 680, "累計銷售票數": 421, "累計銷售金額": 272820}, {"序號": 75, "國別地區": "美國", "中文片名": "去年聖誕節", "上映日期": "2019/12/06", "申請人": "美商美國環球影片股份有限公司台灣分公司", "出品": "UNIVERSAL INTERNATIONAL FILMS LLC", "上映院數": 2, "銷售票數": 90, "週票數變動率": "-44.79%", "銷售金額": 10040, "累計銷售票數": 95874, "累計銷售金額": 22372940}, {"序號": 76, "國別地區": "美國", "中文片名": "野蠻遊戲：全面晉級", "上映日期": "2019/12/04", "申請人": "美商台灣索尼影業發行股份有限公司台灣分公司", "出品": "SONY PICTURES RELEASING INTERNATIONAL CORPORATION.", "上映院數": 8, "銷售票數": 705, "週票數變動率": "-42.64%", "銷售金額": 55250, "累計銷售票數": 809902, "累計銷售金額": 190321800}, {"序號": 77, "國別地區": "英國", "中文片名": "茱莉小姐", "上映日期": "2019/12/04", "申請人": "威秀影城股份有限公司", "出品": "The Royal National Theatre", "上映院數": 3, "銷售票數": 10, "週票數變動率": "0.00%", "銷售金額": 6680, "累計銷售票數": 385, "累計銷售金額": 249980}, {"序號": 78, "國別地區": "英國", "中文片名": "哈利路亞！", "上映日期": "2019/12/04", "申請人": "威秀影城股份有限公司", "出品": "The Royal National Theatre", "上映院數": 1, "銷售票數": 6, "週票數變動率": "0.00%", "銷售金額": 4240, "累計銷售票數": 329, "累計銷售金額": 208200}, {"序號": 79, "國別地區": "中華民國", "中文片名": "狂飆一夢", "上映日期": "2019/11/29", "申請人": "廖建華影像工作室", "出品": "廖建華影像工作室##一顆星工作室有限公司", "上映院數": 7, "銷售票數": 100, "週票數變動率": "-50.98%", "銷售金額": 23545, "累計銷售票數": 1555, "累計銷售金額": 338016}, {"序號": 80, "國別地區": "美國", "中文片名": "賽道狂人", "上映日期": "2019/11/26", "申請人": "博偉電影股份有限公司", "出品": "BUENA VISTA INTERNATIONAL, INC.", "上映院數": 5, "銷售票數": 173, "週票數變動率": "-62.88%", "銷售金額": 14090, "累計銷售票數": 318446, "累計銷售金額": 77714938}, {"序號": 81, "國別地區": "美國", "中文片名": "冰雪奇緣2", "上映日期": "2019/11/21", "申請人": "台灣華特迪士尼股份有限公司", "出品": "BUENA VISTA INTERNATIONAL, INC.", "上映院數": 9, "銷售票數": 1097, "週票數變動率": "3.10%", "銷售金額": 93550, "累計銷售票數": 1452674, "累計銷售金額": 343798473}, {"序號": 82, "國別地區": "日本", "中文片名": "貓咪知道但是貓咪不說", "上映日期": "2019/09/13", "申請人": "可樂藝術文創股份有限公司", "出品": "THE KLOCKWORX CO., LTD", "上映院數": 1, "銷售票數": 8, "週票數變動率": "-55.56%", "銷售金額": 1200, "累計銷售票數": 1271, "累計銷售金額": 268750}, {"序號": 83, "國別地區": "日本", "中文片名": "普羅米亞", "上映日期": "2019/08/16", "申請人": "中影股份有限公司", "出品": "東寶株式會社", "上映院數": 6, "銷售票數": 376, "週票數變動率": "2.45%", "銷售金額": 133790, "累計銷售票數": 79030, "累計銷售金額": 22287880}, {"序號": 84, "國別地區": "法國", "中文片名": "出發吧！我的脫單假期", "上映日期": "2019/08/09", "申請人": "海鵬影業有限公司", "出品": "Le Pacte", "上映院數": 1, "銷售票數": 0, "週票數變動率": "0.00%", "銷售金額": 0, "累計銷售票數": 2353, "累計銷售金額": 513654}, {"序號": 85, "國別地區": "南韓", "中文片名": "寄生上流", "上映日期": "2019/06/28", "申請人": "英屬蓋曼群島商威望國際娛樂股份有限公司台灣分公司", "出品": "CJ ENM CO. LTD", "上映院數": 10, "銷售票數": 153, "週票數變動率": "-24.63%", "銷售金額": 37463, "累計銷售票數": 648718, "累計銷售金額": 151307719}, {"序號": 86, "國別地區": "加拿大", "中文片名": "金錢性騙局", "上映日期": "2019/06/21", "申請人": "佳映娛樂國際股份有限公司", "出品": "Seville International", "上映院數": 1, "銷售票數": 4, "週票數變動率": "0.00%", "銷售金額": 590, "累計銷售票數": 1995, "累計銷售金額": 295268}, {"序號": 87, "國別地區": "美國", "中文片名": "失控危城", "上映日期": "2019/03/29", "申請人": "英屬維京群島商高捷全球開發有限公司 台灣分公司", "出品": "Arclight Films International, Pty., Ltd.", "上映院數": 1, "銷售票數": 17, "週票數變動率": "-19.05%", "銷售金額": 3480, "累計銷售票數": 148481, "累計銷售金額": 33235438}, {"序號": 88, "國別地區": "日本", "中文片名": "假面飯店", "上映日期": "2019/03/15", "申請人": "英屬維京群島商高捷全球開發有限公司 台灣分公司", "出品": "PONY CANYON, INC.", "上映院數": 1, "銷售票數": 7, "週票數變動率": "-53.33%", "銷售金額": 1400, "累計銷售票數": 51012, "累計銷售金額": 11323043}, {"序號": 89, "國別地區": "加拿大", "中文片名": "哈柏太空之旅 3D", "上映日期": "2019/02/04", "申請人": "國際電影事業有限公司", "出品": "IMAX Corporation", "上映院數": 1, "銷售票數": 4, "週票數變動率": "400.00%", "銷售金額": 745, "累計銷售票數": 603, "累計銷售金額": 86610}, {"序號": 90, "國別地區": "加拿大", "中文片名": "深海獵奇 3D", "上映日期": "2019/02/03", "申請人": "國際電影事業有限公司", "出品": "IMAX Corporation", "上映院數": 1, "銷售票數": 0, "週票數變動率": "0.00%", "銷售金額": 0, "累計銷售票數": 1196, "累計銷售金額": 148899}, {"序號": 91, "國別地區": "美國", "中文片名": "潛艦獵殺令", "上映日期": "2018/10/26", "申請人": "英屬維京群島商高捷全球開發有限公司 台灣分公司", "出品": "NU IMAGE INCORPORATED", "上映院數": 1, "銷售票數": 14, "週票數變動率": "-22.22%", "銷售金額": 2530, "累計銷售票數": 330165, "累計銷售金額": 75215898}, {"序號": 92, "國別地區": "日本", "中文片名": "在咖啡冷掉之前", "上映日期": "2018/10/05", "申請人": "英屬維京群島商高捷全球開發有限公司 台灣分公司", "出品": "TOKYO BROADCASTING SYSTEM TELEVISION, INC.", "上映院數": 1, "銷售票數": 18, "週票數變動率": "63.64%", "銷售金額": 3420, "累計銷售票數": 55296, "累計銷售金額": 12315591}, {"序號": 93, "國別地區": "美國", "中文片名": "鬼店", "上映日期": "2018/09/28", "申請人": "美商華納兄弟(遠東)股份有限公司台灣分公司", "出品": "WARNER BROS. PICTURES INTERNATIONAL.", "上映院數": 1, "銷售票數": 1, "週票數變動率": "0.00%", "銷售金額": 220, "累計銷售票數": 5582, "累計銷售金額": 1392651}, {"序號": 94, "國別地區": "日本", "中文片名": "夏日大作戰", "上映日期": "2018/08/10", "申請人": "傳影互動股份有限公司", "出品": "STUDIO CHIZU LLP", "上映院數": 5, "銷售票數": 68, "週票數變動率": "21.43%", "銷售金額": 31465, "累計銷售票數": 8215, "累計銷售金額": 3580596}, {"序號": 95, "國別地區": "法國", "中文片名": "醫生敲愛錢", "上映日期": "2018/06/22", "申請人": "聯影企業股份有限公司", "出品": "TF1 DROITS AUDIOVISUELS", "上映院數": 1, "銷售票數": 4, "週票數變動率": "0.00%", "銷售金額": 550, "累計銷售票數": 1218, "累計銷售金額": 244070}, {"序號": 96, "國別地區": "美國", "中文片名": "噤界", "上映日期": "2018/04/04", "申請人": "美商美國派拉蒙影片股份有限公司台灣分公司", "出品": "PARAMOUNT PICTURES CORPORATION", "上映院數": 5, "銷售票數": 67, "週票數變動率": "6.35%", "銷售金額": 14520, "累計銷售票數": 315677, "累計銷售金額": 72400984}, {"序號": 97, "國別地區": "美國", "中文片名": "出神入化2", "上映日期": "2016/06/08", "申請人": "英屬維京群島商高捷全球開發有限公司台灣分公司", "出品": "SUMMIT ENTERTAINMENT, LLC", "上映院數": 4, "銷售票數": 48, "週票數變動率": "37.14%", "銷售金額": 10070, "累計銷售票數": 939577, "累計銷售金額": 223341879}, {"序號": 98, "國別地區": "英國", "中文片名": "李爾王", "上映日期": "2016/04/23", "申請人": "威秀影城股份有限公司", "出品": "THE ROYAL NATIONAL THEATRE", "上映院數": 3, "銷售票數": 5, "週票數變動率": "-64.29%", "銷售金額": 3760, "累計銷售票數": 1491, "累計銷售金額": 1036020}, {"序號": 99, "國別地區": "美國", "中文片名": "刺激1995", "上映日期": "1995/03/10", "申請人": "美商華納兄弟（遠東）股份有限公司台灣分公司", "出品": "WARNER BROS. PICTURES INTERNATIONAL.", "上映院數": 21, "銷售票數": 4113, "週票數變動率": "-45.29%", "銷售金額": 993521, "累計銷售票數": 18388, "累計銷售金額": 4491010}]