[
  {
    "field": "序號",
    "sortable": true,
    "width": 60
  },
  {
    "field": "國別地區",
    "sortable": true,
    "width": 95,
    "filter": "agTextColumnFilter"
  },
  {
    "field": "中文片名",
    "filter": "agTextColumnFilter"
  },
  {
    "field": "上映日期",
    "sortable": true,
    "width": 100,
    "filter": "agTextColumnFilter"
  },
  {
    "field": "上映院數",
    "sortable": true,
    "width": 100,
    "filter": "agNumberColumnFilter"
  },
  {
    "field": "銷售票數",
    "sortable": true,
    "width": 100,
    "filter": "agNumberColumnFilter"
  },
  {
    "field": "銷售金額",
    "sortable": true,
    "width": 100,
    "filter": "agNumberColumnFilter"
  },
  {
    "field": "累計銷售票數",
    "sortable": true,
    "width": 130,
    "filter": "agNumberColumnFilter"
  },
  {
    "field": "累計銷售金額",
    "sortable": true,
    "width": 130,
    "filter": "agNumberColumnFilter"
  },
  {
    "field": "出品",
    "sortable": true,
    "filter": "agTextColumnFilter"
  },
  {
    "field": "申請人",
    "sortable": true,
    "filter": "agTextColumnFilter"
  }
]
